<?xml version="1.0" encoding="UTF-8" standalone="yes"?><imgdir name="8880850.img"><imgdir name="info"><int name="level" value="275"/><int name="maxHP" value="2100000000"/><int name="maxMP" value="100000"/><int name="mpRecovery" value="10000"/><int name="speed" value="-20"/><int name="PADamage" value="22000"/><int name="MADamage" value="24000"/><int name="PDRate" value="300"/><int name="MDRate" value="300"/><int name="acc" value="9999"/><string name="elemAttr" value="P2H2F2I2S2L2D2"/><int name="eva" value="750"/><int name="pushed" value="1000000000"/><float name="fs" value="10.0"/><int name="exp" value="0"/><int name="summonType" value="1"/><int name="category" value="8"/><int name="firstAttack" value="1"/><string name="mobType" value="7N"/><int name="boss" value="1"/><string name="defaultHP" value="측정불가"/><string name="defaultMP" value="측정불가"/><int name="showNotRemoteDam" value="1"/><int name="isRemoteRange" value="1"/><int name="ignoreMoveImpact" value="1"/><imgdir name="attack"><imgdir name="0"><int name="action" value="1"/><int name="attackRatio" value="100"/><int name="type" value="0"/><int name="conMP" value="1"/><int name="magic" value="1"/><int name="fixDamR" value="100"/><int name="cooltime" value="60000"/><int name="notMissAttack" value="1"/><int name="attackCount" value="10"/></imgdir><imgdir name="1"><int name="action" value="2"/><int name="attackRatio" value="100"/><int name="type" value="0"/><int name="conMP" value="1"/><int name="magic" value="1"/><int name="fixDamR" value="40"/><int name="cooltime" value="15000"/><int name="notMissAttack" value="1"/><int name="attackCount" value="1"/></imgdir><imgdir name="2"><int name="action" value="3"/><int name="attackRatio" value="100"/><int name="type" value="0"/><int name="conMP" value="1"/><int name="magic" value="1"/><int name="fixDamR" value="40"/><int name="cooltime" value="15000"/><int name="notMissAttack" value="1"/><int name="attackCount" value="1"/></imgdir><imgdir name="3"><int name="action" value="4"/><int name="attackRatio" value="100"/><int name="type" value="0"/><int name="conMP" value="0"/><int name="magic" value="1"/><int name="fixDamR" value="20"/><int name="cooltime" value="25000"/><int name="rush" value="1"/></imgdir></imgdir><imgdir name="firstAttackRange"><vector name="lt" x="-2500" y="-1000"/><vector name="rb" x="2500" y="1000"/></imgdir><int name="hpTagColor" value="1"/><int name="hpTagBgcolor" value="5"/><int name="delAtomOnDead" value="1"/><int name="ignoreFieldOut" value="1"/><int name="ignoreSlow" value="1"/><int name="ignoreMovable" value="1"/><string name="ignoreMoveableMsg" value="사도의 힘을 얻은 괴물을 행동 불가 상태로 만들 수는 없다."/><string name="ignoreSlowMsg" value="사도의 힘을 얻은 괴물은 이동속도가 저하되지 않는다."/></imgdir><imgdir name="regen"><canvas name="0" width="1" height="1"><int name="delay" value="900"/></canvas><canvas name="1" width="1" height="1"><vector name="origin" x="386" y="1333"/><int name="z" value="0"/><int name="delay" value="60"/><string name="_hash" value="07ecbef747b03bd7c93ee3b343c07ed3e560f7106a37c8129dd7bba0bd7c5841"/><string name="_outlink" value="Mob/8880831.img/regen/1"/></canvas><canvas name="2" width="1" height="1"><vector name="origin" x="386" y="1319"/><int name="z" value="0"/><int name="delay" value="60"/><string name="_hash" value="e4f98b4d14fd3f6f62b86a4bc0bf5dde3acc31f0cb5247812f734c003ab10292"/><string name="_outlink" value="Mob/8880831.img/regen/2"/></canvas><canvas name="3" width="1" height="1"><vector name="origin" x="386" y="1303"/><int name="z" value="0"/><int name="delay" value="60"/><string name="_hash" value="c9659e7ee5319503294570900605d10c2264cd6a9b6e96cfc294616ebeb35d58"/><string name="_outlink" value="Mob/8880831.img/regen/3"/></canvas><canvas name="4" width="1" height="1"><vector name="origin" x="386" y="1289"/><int name="z" value="0"/><int name="delay" value="60"/><string name="_hash" value="4ed1d1bcf04b90475736e1741712a3cd5b3c6fa78feb61e51fef2e71c7e8701a"/><string name="_outlink" value="Mob/8880831.img/regen/4"/></canvas><canvas name="5" width="1" height="1"><vector name="origin" x="385" y="1275"/><int name="z" value="0"/><int name="delay" value="60"/><string name="_hash" value="683b15c4be4992e4e15c4e5b7cc55bc8cea247aa9aa4ae181de9eae4be9f8fce"/><string name="_outlink" value="Mob/8880831.img/regen/5"/></canvas><canvas name="6" width="1" height="1"><vector name="origin" x="385" y="1259"/><int name="z" value="0"/><int name="delay" value="60"/><string name="_hash" value="2b442260519e8359f4ed92db40e29ab225a714d5afb376ad3d545ff42bde06dd"/><string name="_outlink" value="Mob/8880831.img/regen/6"/></canvas><canvas name="7" width="1" height="1"><vector name="origin" x="384" y="1243"/><int name="z" value="0"/><int name="delay" value="60"/><string name="_hash" value="3d7ca39d8aa23d7de75da5ac56fd69c165244873a524a75bd31a2d5319ca0b35"/><string name="_outlink" value="Mob/8880831.img/regen/7"/></canvas><canvas name="8" width="1" height="1"><vector name="origin" x="383" y="1267"/><int name="z" value="0"/><int name="delay" value="60"/><string name="_hash" value="dd73e9618656245a804a7469f3b6171ac06f2b55486cd08ad0d7247893055103"/><string name="_outlink" value="Mob/8880831.img/regen/8"/></canvas><canvas name="9" width="1" height="1"><vector name="origin" x="382" y="1350"/><int name="z" value="0"/><int name="delay" value="60"/><string name="_hash" value="2a11400826248bc89d37ecaca1bb554b9626fb90132b31cd138afd6c91511c0c"/><string name="_outlink" value="Mob/8880831.img/regen/9"/></canvas><canvas name="10" width="1" height="1"><vector name="origin" x="381" y="1333"/><int name="z" value="0"/><int name="delay" value="60"/><string name="_hash" value="6a1a2f3b4d5fa76d9c4f8269bac03168d5d9ddf61d8100e07ad647588e282da2"/><string name="_outlink" value="Mob/8880831.img/regen/10"/></canvas><canvas name="11" width="1" height="1"><vector name="origin" x="391" y="1583"/><int name="z" value="0"/><int name="delay" value="60"/><string name="_hash" value="a6e796601aafa2dd523355ec0418d8d04c5145aefade8d0f1a76f21a497377ae"/><string name="_outlink" value="Mob/8880831.img/regen/11"/></canvas><canvas name="12" width="1" height="1"><vector name="origin" x="394" y="1565"/><int name="z" value="0"/><int name="delay" value="60"/><string name="_hash" value="e869f427ff1a504b1a3defe29bdac2eef57516d5c5a076556fb6b6a94c511908"/><string name="_outlink" value="Mob/8880831.img/regen/12"/></canvas><canvas name="13" width="1" height="1"><vector name="origin" x="395" y="1549"/><int name="z" value="0"/><int name="delay" value="60"/><string name="_hash" value="ed0afc488ad1a8d124a88fb7ac7a3cb7f24d5e5e36ee0ae083e7e13caecbab86"/><string name="_outlink" value="Mob/8880831.img/regen/13"/></canvas><canvas name="14" width="1" height="1"><vector name="origin" x="390" y="1531"/><int name="z" value="0"/><int name="delay" value="60"/><string name="_hash" value="8ed1765218c66f6bd8ace58789b0ca219e1f22e11f73174d0166c2fbcd2ec6ef"/><string name="_outlink" value="Mob/8880831.img/regen/14"/></canvas><canvas name="15" width="1" height="1"><vector name="origin" x="381" y="1517"/><int name="z" value="0"/><int name="delay" value="60"/><string name="_hash" value="8414fc436a0d94b1c4dd85f89d255fc1606c485f83af7f37fe20c12b825e41c9"/><string name="_outlink" value="Mob/8880831.img/regen/15"/></canvas><canvas name="16" width="1" height="1"><vector name="origin" x="377" y="1584"/><int name="z" value="0"/><int name="delay" value="60"/><string name="_hash" value="b8ede222ca2006147108cad9420510572d507708984f2edfd9c635c98a160766"/><string name="_outlink" value="Mob/8880831.img/regen/16"/></canvas><canvas name="17" width="1" height="1"><vector name="origin" x="374" y="1567"/><int name="z" value="0"/><int name="delay" value="60"/><string name="_hash" value="7bc9fe72496c30e36b31f9ee4c84dce2c1ac1e8172696389548061253acd2453"/><string name="_outlink" value="Mob/8880831.img/regen/17"/></canvas><canvas name="18" width="1" height="1"><vector name="origin" x="372" y="1551"/><int name="z" value="0"/><int name="delay" value="60"/><string name="_hash" value="d803769e96c3512cd06dba1bfc17a41bee16bdb53b6bad45324ca77777d3c8d6"/><string name="_outlink" value="Mob/8880831.img/regen/18"/></canvas><canvas name="19" width="1" height="1"><vector name="origin" x="371" y="1537"/><int name="z" value="0"/><int name="delay" value="60"/><string name="_hash" value="649702bc41495559f42d39563ab1fc6e634205eb095effa49e0983da6533ed30"/><string name="_outlink" value="Mob/8880831.img/regen/19"/></canvas><canvas name="20" width="1" height="1"><vector name="origin" x="794" y="1454"/><int name="z" value="0"/><int name="delay" value="60"/><string name="_hash" value="8bf9e00bfb90d1d0223e38ca342d2d376aad808793a316aeb82e04029891c9d4"/><string name="_outlink" value="Mob/8880831.img/regen/20"/></canvas><canvas name="21" width="1" height="1"><vector name="origin" x="794" y="1454"/><int name="z" value="0"/><int name="delay" value="60"/><string name="_hash" value="1636a2c8837128269f49c6b79ae85532d5789bf1dd3a2f13ed83e890f0e7432a"/><string name="_outlink" value="Mob/8880831.img/regen/21"/></canvas><canvas name="22" width="1" height="1"><vector name="origin" x="794" y="1454"/><int name="z" value="0"/><int name="delay" value="60"/><string name="_hash" value="57bb4b4a585b4dec0da214a7fda24dc50ecdfc401a55e5f2c0baa5b39a78dfc9"/><string name="_outlink" value="Mob/8880831.img/regen/22"/></canvas><canvas name="23" width="1" height="1"><vector name="origin" x="794" y="1262"/><int name="z" value="0"/><int name="delay" value="60"/><string name="_hash" value="548b95d201200f48eccf797fddd3b885e44b22d8c69f5fcfc61b9f09f91a7b0b"/><string name="_outlink" value="Mob/8880831.img/regen/23"/></canvas><canvas name="24" width="1" height="1"><vector name="origin" x="794" y="1454"/><int name="z" value="0"/><int name="delay" value="60"/><string name="_hash" value="e9f9232bbc5359339745b7b151ef043d80c7193a5b7d2610049b7a9c8b2faf0f"/><string name="_outlink" value="Mob/8880831.img/regen/24"/></canvas><canvas name="25" width="1" height="1"><vector name="origin" x="794" y="1412"/><int name="z" value="0"/><int name="delay" value="60"/><string name="_hash" value="74e20989c4b95848d009409c504f0a95b7983c9385671f51599bf0db5ba0a9a9"/><string name="_outlink" value="Mob/8880831.img/regen/25"/></canvas><canvas name="26" width="1" height="1"><vector name="origin" x="704" y="1072"/><int name="z" value="0"/><int name="delay" value="60"/><string name="_hash" value="b9c948ecafeaa42a3a55831269e55f9dbab50829e36b3dd3cef53807d942c2bb"/><string name="_outlink" value="Mob/8880831.img/regen/26"/></canvas><canvas name="27" width="1" height="1"><vector name="origin" x="700" y="821"/><int name="z" value="0"/><int name="delay" value="60"/><string name="_hash" value="c1ab6986028c6ae1d4edce275a6aafa38c2398b2b37f9af7def3c63e95631818"/><string name="_outlink" value="Mob/8880831.img/regen/27"/></canvas></imgdir><imgdir name="stand"><canvas name="0" width="1" height="1"><vector name="origin" x="397" y="523"/><int name="z" value="0"/><int name="delay" value="90"/><vector name="lt" x="-183" y="-408"/><vector name="rb" x="180" y="7"/><vector name="head" x="-75" y="-333"/><string name="_hash" value="1c4a51db3b721cb0bb9b6c0fd2dd9d8090ae30cf0a9bb4f1d95566611045bd82"/><string name="_outlink" value="Mob/8880831.img/stand/0"/></canvas><canvas name="1" width="1" height="1"><vector name="origin" x="397" y="526"/><int name="z" value="0"/><int name="delay" value="90"/><vector name="lt" x="-183" y="-408"/><vector name="rb" x="180" y="7"/><vector name="head" x="-75" y="-333"/><string name="_hash" value="37ea2dde17aa231816711267c1697506e573613ea4dc0a73217ae84841e8827f"/><string name="_outlink" value="Mob/8880831.img/stand/1"/></canvas><canvas name="2" width="1" height="1"><vector name="origin" x="398" y="529"/><int name="z" value="0"/><int name="delay" value="90"/><vector name="lt" x="-183" y="-408"/><vector name="rb" x="180" y="7"/><vector name="head" x="-75" y="-333"/><string name="_hash" value="10e7ee15a815dde8dc9bc9f4ed8f6795f644832c5d900336093dd4717a5ae14b"/><string name="_outlink" value="Mob/8880831.img/stand/2"/></canvas><canvas name="3" width="1" height="1"><vector name="origin" x="399" y="533"/><int name="z" value="0"/><int name="delay" value="90"/><vector name="lt" x="-183" y="-408"/><vector name="rb" x="180" y="7"/><vector name="head" x="-75" y="-333"/><string name="_hash" value="44dfcdfbbba09a3d863037811bf59e8ccd50a3d6b1a94ec77da6b4fbfce769f0"/><string name="_outlink" value="Mob/8880831.img/stand/3"/></canvas><canvas name="4" width="1" height="1"><vector name="origin" x="400" y="536"/><int name="z" value="0"/><int name="delay" value="90"/><vector name="lt" x="-183" y="-408"/><vector name="rb" x="180" y="7"/><vector name="head" x="-75" y="-333"/><string name="_hash" value="f1d7696ada2ffc6c6f663b745f18451e0f06d6c06fc81c02f9c7c53480b2c7e7"/><string name="_outlink" value="Mob/8880831.img/stand/4"/></canvas><canvas name="5" width="1" height="1"><vector name="origin" x="401" y="539"/><int name="z" value="0"/><int name="delay" value="90"/><vector name="lt" x="-183" y="-408"/><vector name="rb" x="180" y="7"/><vector name="head" x="-75" y="-333"/><string name="_hash" value="2820ec870535be40ff11df9a3440f38036bbb0cc39a59351cab4b1b723454eda"/><string name="_outlink" value="Mob/8880831.img/stand/5"/></canvas><canvas name="6" width="1" height="1"><vector name="origin" x="401" y="542"/><int name="z" value="0"/><int name="delay" value="90"/><vector name="lt" x="-183" y="-408"/><vector name="rb" x="180" y="7"/><vector name="head" x="-75" y="-333"/><string name="_hash" value="d1d463884a29f435506c2f2b2f343592ec30b950bc42879bd619926b6800df4c"/><string name="_outlink" value="Mob/8880831.img/stand/6"/></canvas><canvas name="7" width="1" height="1"><vector name="origin" x="402" y="545"/><int name="z" value="0"/><int name="delay" value="90"/><vector name="lt" x="-183" y="-408"/><vector name="rb" x="180" y="7"/><vector name="head" x="-75" y="-333"/><string name="_hash" value="4c3ac77f0d5f8c719961aa2ebe5cae9ba21bdc98b6bac618449b044e2b371181"/><string name="_outlink" value="Mob/8880831.img/stand/7"/></canvas><canvas name="8" width="1" height="1"><vector name="origin" x="402" y="549"/><int name="z" value="0"/><int name="delay" value="90"/><vector name="lt" x="-183" y="-408"/><vector name="rb" x="180" y="7"/><vector name="head" x="-75" y="-333"/><string name="_hash" value="568f8489584a059b1e8923cb0d42a52e220def4a014bbef11e14f51f87d3b553"/><string name="_outlink" value="Mob/8880831.img/stand/8"/></canvas><canvas name="9" width="1" height="1"><vector name="origin" x="401" y="552"/><int name="z" value="0"/><int name="delay" value="90"/><vector name="lt" x="-183" y="-408"/><vector name="rb" x="180" y="7"/><vector name="head" x="-75" y="-333"/><string name="_hash" value="90b10a78fff0f4d3933c4324510449846c418a7cc30f3b767a7c47d720844ade"/><string name="_outlink" value="Mob/8880831.img/stand/9"/></canvas><canvas name="10" width="1" height="1"><vector name="origin" x="400" y="504"/><int name="z" value="0"/><int name="delay" value="90"/><vector name="lt" x="-183" y="-408"/><vector name="rb" x="180" y="7"/><vector name="head" x="-75" y="-333"/><string name="_hash" value="344a5f7723ac58f38cd25a523d9e7020ed611971f8abc769b6a849c628959c89"/><string name="_outlink" value="Mob/8880831.img/stand/10"/></canvas><canvas name="11" width="1" height="1"><vector name="origin" x="400" y="507"/><int name="z" value="0"/><int name="delay" value="90"/><vector name="lt" x="-183" y="-408"/><vector name="rb" x="180" y="7"/><vector name="head" x="-75" y="-333"/><string name="_hash" value="b49b27b67e93a9dfe5b525fbfdc3ac968508838ff9ba82702d9a5bc7766cf0f9"/><string name="_outlink" value="Mob/8880831.img/stand/11"/></canvas><canvas name="12" width="1" height="1"><vector name="origin" x="399" y="511"/><int name="z" value="0"/><int name="delay" value="90"/><vector name="lt" x="-183" y="-408"/><vector name="rb" x="180" y="7"/><vector name="head" x="-75" y="-333"/><string name="_hash" value="8086ae5af1f965141ddb5b427e754e40a64cacda4142e62a96eedca297290bfe"/><string name="_outlink" value="Mob/8880831.img/stand/12"/></canvas><canvas name="13" width="1" height="1"><vector name="origin" x="398" y="514"/><int name="z" value="0"/><int name="delay" value="90"/><vector name="lt" x="-183" y="-408"/><vector name="rb" x="180" y="7"/><vector name="head" x="-75" y="-333"/><string name="_hash" value="9a52c59abe1bd39229d1a15af2b619a1590fc7609ae8c2717af0b3c2da390582"/><string name="_outlink" value="Mob/8880831.img/stand/13"/></canvas><canvas name="14" width="1" height="1"><vector name="origin" x="397" y="517"/><int name="z" value="0"/><int name="delay" value="90"/><vector name="lt" x="-183" y="-408"/><vector name="rb" x="180" y="7"/><vector name="head" x="-75" y="-333"/><string name="_hash" value="418c004abb3f97a2d7d21bb69da3fc92e9976e6daafb1a182fe4e43eeaba52c1"/><string name="_outlink" value="Mob/8880831.img/stand/14"/></canvas><canvas name="15" width="1" height="1"><vector name="origin" x="397" y="520"/><int name="z" value="0"/><int name="delay" value="90"/><vector name="lt" x="-183" y="-408"/><vector name="rb" x="180" y="7"/><vector name="head" x="-75" y="-333"/><string name="_hash" value="02a11a989017b4f7f37b20f456387fec17b89eb87d9bd6f8983120a2cc02f24b"/><string name="_outlink" value="Mob/8880831.img/stand/15"/></canvas></imgdir><imgdir name="move"><canvas name="0" width="1" height="1"><vector name="origin" x="397" y="523"/><int name="z" value="0"/><int name="delay" value="90"/><vector name="lt" x="-183" y="-408"/><vector name="rb" x="180" y="7"/><vector name="head" x="-75" y="-333"/><string name="_hash" value="c6b4f9584acdea3cb1db701e4434bc7f01b3f578ef92843208b30489753f5910"/><string name="_outlink" value="Mob/8880831.img/move/0"/></canvas><canvas name="1" width="1" height="1"><vector name="origin" x="397" y="526"/><int name="z" value="0"/><int name="delay" value="90"/><vector name="lt" x="-183" y="-408"/><vector name="rb" x="180" y="7"/><vector name="head" x="-75" y="-333"/><string name="_hash" value="3f902c9139dcc410b6619931dc87b40a24f65e81c0fb10aa92018bcfc70af01b"/><string name="_outlink" value="Mob/8880831.img/move/1"/></canvas><canvas name="2" width="1" height="1"><vector name="origin" x="398" y="529"/><int name="z" value="0"/><int name="delay" value="90"/><vector name="lt" x="-183" y="-408"/><vector name="rb" x="180" y="7"/><vector name="head" x="-75" y="-333"/><string name="_hash" value="cbbb7c7c27a77b5fc15c53ed5b6deb6a05a5e30309ee910629a343bc93c041c2"/><string name="_outlink" value="Mob/8880831.img/move/2"/></canvas><canvas name="3" width="1" height="1"><vector name="origin" x="399" y="533"/><int name="z" value="0"/><int name="delay" value="90"/><vector name="lt" x="-183" y="-408"/><vector name="rb" x="180" y="7"/><vector name="head" x="-75" y="-333"/><string name="_hash" value="8993d967e4da8f944ec58d7dc9886168543791d2d240ffd4e4502a44363fd68e"/><string name="_outlink" value="Mob/8880831.img/move/3"/></canvas><canvas name="4" width="1" height="1"><vector name="origin" x="400" y="536"/><int name="z" value="0"/><int name="delay" value="90"/><vector name="lt" x="-183" y="-408"/><vector name="rb" x="180" y="7"/><vector name="head" x="-75" y="-333"/><string name="_hash" value="7ff492174bbda0f85ce6012dc5e9eb01fd1bd742d6f9760d2ec90115644f8bab"/><string name="_outlink" value="Mob/8880831.img/move/4"/></canvas><canvas name="5" width="1" height="1"><vector name="origin" x="401" y="539"/><int name="z" value="0"/><int name="delay" value="90"/><vector name="lt" x="-183" y="-408"/><vector name="rb" x="180" y="7"/><vector name="head" x="-75" y="-333"/><string name="_hash" value="ee3483ddf5507f0470af859539fa272d0d6b0646ef9ca7daea1eb4bd60448de2"/><string name="_outlink" value="Mob/8880831.img/move/5"/></canvas><canvas name="6" width="1" height="1"><vector name="origin" x="401" y="542"/><int name="z" value="0"/><int name="delay" value="90"/><vector name="lt" x="-183" y="-408"/><vector name="rb" x="180" y="7"/><vector name="head" x="-75" y="-333"/><string name="_hash" value="5cbcae0fb5c578e780e8befb044851b104c34c2b0a25c923114aab89e999bc43"/><string name="_outlink" value="Mob/8880831.img/move/6"/></canvas><canvas name="7" width="1" height="1"><vector name="origin" x="402" y="545"/><int name="z" value="0"/><int name="delay" value="90"/><vector name="lt" x="-183" y="-408"/><vector name="rb" x="180" y="7"/><vector name="head" x="-75" y="-333"/><string name="_hash" value="d772211eb13c01935d70f872ff4078bafd62b43af1a4530b2c8895a2820bef20"/><string name="_outlink" value="Mob/8880831.img/move/7"/></canvas><canvas name="8" width="1" height="1"><vector name="origin" x="402" y="549"/><int name="z" value="0"/><int name="delay" value="90"/><vector name="lt" x="-183" y="-408"/><vector name="rb" x="180" y="7"/><vector name="head" x="-75" y="-333"/><string name="_hash" value="df17c363302b7de4699a73be4256d4bbea788b2d30ea30a5f292b72b49e1549e"/><string name="_outlink" value="Mob/8880831.img/move/8"/></canvas><canvas name="9" width="1" height="1"><vector name="origin" x="401" y="552"/><int name="z" value="0"/><int name="delay" value="90"/><vector name="lt" x="-183" y="-408"/><vector name="rb" x="180" y="7"/><vector name="head" x="-75" y="-333"/><string name="_hash" value="3884f70fa89788a16a3c05893e56911b195aa651e90538d697a7f05fc0ea6e38"/><string name="_outlink" value="Mob/8880831.img/move/9"/></canvas><canvas name="10" width="1" height="1"><vector name="origin" x="400" y="504"/><int name="z" value="0"/><int name="delay" value="90"/><vector name="lt" x="-183" y="-408"/><vector name="rb" x="180" y="7"/><vector name="head" x="-75" y="-333"/><string name="_hash" value="3be321a7ef9859d3f79c64fee8ca0b1f02eeb314dd213ea571f24ceed65e341e"/><string name="_outlink" value="Mob/8880831.img/move/10"/></canvas><canvas name="11" width="1" height="1"><vector name="origin" x="400" y="507"/><int name="z" value="0"/><int name="delay" value="90"/><vector name="lt" x="-183" y="-408"/><vector name="rb" x="180" y="7"/><vector name="head" x="-75" y="-333"/><string name="_hash" value="f1c5bc766c4fe976a185e2ff16ddd2c506ddba1250acc57d48a35b6b4b618749"/><string name="_outlink" value="Mob/8880831.img/move/11"/></canvas><canvas name="12" width="1" height="1"><vector name="origin" x="399" y="511"/><int name="z" value="0"/><int name="delay" value="90"/><vector name="lt" x="-183" y="-408"/><vector name="rb" x="180" y="7"/><vector name="head" x="-75" y="-333"/><string name="_hash" value="c66539fc6c157dc79015a2fd8691ac2635a89dd1312bc2ad14298557c6d466e1"/><string name="_outlink" value="Mob/8880831.img/move/12"/></canvas><canvas name="13" width="1" height="1"><vector name="origin" x="398" y="514"/><int name="z" value="0"/><int name="delay" value="90"/><vector name="lt" x="-183" y="-408"/><vector name="rb" x="180" y="7"/><vector name="head" x="-75" y="-333"/><string name="_hash" value="8748de1a18e666f6ad52783b89cc06e5292b421663723264b0af0d78f44c8f59"/><string name="_outlink" value="Mob/8880831.img/move/13"/></canvas><canvas name="14" width="1" height="1"><vector name="origin" x="397" y="517"/><int name="z" value="0"/><int name="delay" value="90"/><vector name="lt" x="-183" y="-408"/><vector name="rb" x="180" y="7"/><vector name="head" x="-75" y="-333"/><string name="_hash" value="db767eadf5f4b57e75be6d5b200f99a856b75f40eb19825aa4a908b411092265"/><string name="_outlink" value="Mob/8880831.img/move/14"/></canvas><canvas name="15" width="1" height="1"><vector name="origin" x="397" y="520"/><int name="z" value="0"/><int name="delay" value="90"/><vector name="lt" x="-183" y="-408"/><vector name="rb" x="180" y="7"/><vector name="head" x="-75" y="-333"/><string name="_hash" value="1c57d56dbcc439f810cb9855662f15ac56fbe8406c4fd288af5ee1935fad7b86"/><string name="_outlink" value="Mob/8880831.img/move/15"/></canvas></imgdir><imgdir name="flip"><canvas name="0" width="1" height="1"><vector name="origin" x="353" y="526"/><int name="z" value="0"/><int name="delay" value="30"/><vector name="lt" x="-183" y="-408"/><vector name="rb" x="180" y="7"/><vector name="head" x="-75" y="-333"/><string name="_hash" value="d15399d5e2ee5711f443cf2f251d2d24bc2ea54448ca8554fce8777adfd75495"/><string name="_outlink" value="Mob/8880831.img/flip/0"/></canvas><canvas name="1" width="1" height="1"><vector name="origin" x="379" y="539"/><int name="z" value="0"/><int name="delay" value="30"/><vector name="lt" x="-183" y="-408"/><vector name="rb" x="180" y="7"/><vector name="head" x="-75" y="-333"/><string name="_hash" value="04375eb808cb0db2043eb961ef4445359ac0c10b82050a701bfb5552e4ee0540"/><string name="_outlink" value="Mob/8880831.img/flip/1"/></canvas><canvas name="2" width="1" height="1"><vector name="origin" x="395" y="517"/><int name="z" value="0"/><int name="delay" value="30"/><vector name="lt" x="-183" y="-408"/><vector name="rb" x="180" y="7"/><vector name="head" x="-75" y="-333"/><string name="_hash" value="2c6803c8bfac597f652beec6553b27157d4677a47a4a9bbab916ceaf62794b17"/><string name="_outlink" value="Mob/8880831.img/flip/2"/></canvas><imgdir name="effect"><canvas name="0" width="1" height="1"><vector name="origin" x="189" y="100"/><int name="z" value="0"/><int name="delay" value="60"/><string name="_hash" value="ecc75ecc494f874904fbb1ffd900647c50d3f249daa2546d1fc8fb89f9fb0c2d"/><string name="_outlink" value="Mob/8880831.img/flip/effect/0"/></canvas><canvas name="1" width="1" height="1"><vector name="origin" x="278" y="118"/><int name="z" value="0"/><int name="delay" value="60"/><string name="_hash" value="6e619e0ecc01925dd303cc8a601897f83354b148cce82b68084391c93ff9f282"/><string name="_outlink" value="Mob/8880831.img/flip/effect/1"/></canvas><canvas name="2" width="1" height="1"><vector name="origin" x="292" y="122"/><int name="z" value="0"/><int name="delay" value="60"/><string name="_hash" value="7aa911e4723202365a8a5f283feb140e41b125b5326500995c57d7f94d222ebe"/><string name="_outlink" value="Mob/8880831.img/flip/effect/2"/></canvas><canvas name="3" width="1" height="1"><vector name="origin" x="302" y="122"/><int name="z" value="0"/><int name="delay" value="60"/><string name="_hash" value="15f9e2fdb44190e94ce5bd36909457667cccdd7b2ea3900e6285926631c0b442"/><string name="_outlink" value="Mob/8880831.img/flip/effect/3"/></canvas><canvas name="4" width="1" height="1"><vector name="origin" x="309" y="120"/><int name="z" value="0"/><int name="delay" value="60"/><string name="_hash" value="f7ae4adfd8aeb3c7ff57cec030292112146dd2e0c5c9baeb6b37add8c8fbd280"/><string name="_outlink" value="Mob/8880831.img/flip/effect/4"/></canvas><canvas name="5" width="1" height="1"><vector name="origin" x="312" y="126"/><int name="z" value="0"/><int name="delay" value="60"/><string name="_hash" value="b91edfcbbd57778740e2793062a5c6c8a6053e2c60917a28e5bd1ebcd2770ca2"/><string name="_outlink" value="Mob/8880831.img/flip/effect/5"/></canvas><canvas name="6" width="1" height="1"><vector name="origin" x="317" y="126"/><int name="z" value="0"/><int name="delay" value="60"/><string name="_hash" value="99dbfe2e157def2f2e0ee08135f36089bd3da606b10f4d3a50327caa202ebb46"/><string name="_outlink" value="Mob/8880831.img/flip/effect/6"/></canvas><canvas name="7" width="1" height="1"><vector name="origin" x="321" y="128"/><int name="z" value="0"/><int name="delay" value="60"/><string name="_hash" value="8ed0ee114d34fcf06b4f8314cb238cfa06a6ec5fd96139f05c23dbaf0829e3b9"/><string name="_outlink" value="Mob/8880831.img/flip/effect/7"/></canvas></imgdir></imgdir><imgdir name="hit1"><canvas name="0" width="1" height="1"><vector name="origin" x="397" y="523"/><int name="z" value="0"/><int name="delay" value="90"/><vector name="lt" x="-183" y="-408"/><vector name="rb" x="180" y="7"/><vector name="head" x="-75" y="-333"/><string name="_outlink" value="Mob/8880831.img/stand/0"/></canvas></imgdir><imgdir name="die1"><canvas name="0" width="1" height="1"><vector name="origin" x="370" y="512"/><int name="z" value="0"/><int name="delay" value="90"/><string name="_hash" value="7f02c6d39e454c5f152b8151bbca3decb76434736a2f14f14b35027be349062b"/><string name="_outlink" value="Mob/8880831.img/die1/0"/></canvas><canvas name="1" width="1" height="1"><vector name="origin" x="367" y="516"/><int name="z" value="0"/><int name="delay" value="90"/><string name="_hash" value="6e52f5852282380564c9e30407026d4853aa91a06ce62b0a1e3c880372cb46c8"/><string name="_outlink" value="Mob/8880831.img/die1/1"/></canvas><canvas name="2" width="1" height="1"><vector name="origin" x="370" y="519"/><int name="z" value="0"/><int name="delay" value="90"/><string name="_hash" value="feb9981ea8b632ef4c7dfcfb82a358615f3b498b87fd400c841ef2ee4eba5336"/><string name="_outlink" value="Mob/8880831.img/die1/2"/></canvas><canvas name="3" width="1" height="1"><vector name="origin" x="372" y="523"/><int name="z" value="0"/><int name="delay" value="90"/><string name="_hash" value="45c2dffa4fc5e3c4caf7168f7e2e8391e9397958e97cdfced6ae8d8d220948f2"/><string name="_outlink" value="Mob/8880831.img/die1/3"/></canvas><canvas name="4" width="1" height="1"><vector name="origin" x="374" y="526"/><int name="z" value="0"/><int name="delay" value="90"/><string name="_hash" value="23645335714a942cf44eb4addc411f54a08c9c756d8c3316180d20eabea8858c"/><string name="_outlink" value="Mob/8880831.img/die1/4"/></canvas><canvas name="5" width="1" height="1"><vector name="origin" x="376" y="529"/><int name="z" value="0"/><int name="delay" value="90"/><string name="_hash" value="e83ee1b83d31a02728861a662feac8d029737ff495a59182b90df2c622e3c0e3"/><string name="_outlink" value="Mob/8880831.img/die1/5"/></canvas><canvas name="6" width="1" height="1"><vector name="origin" x="377" y="532"/><int name="z" value="0"/><int name="delay" value="90"/><string name="_hash" value="4043ef49da168296f74c1523146b045d53ac1007a4e43033336afe6be1ee9384"/><string name="_outlink" value="Mob/8880831.img/die1/6"/></canvas><canvas name="7" width="1" height="1"><vector name="origin" x="379" y="535"/><int name="z" value="0"/><int name="delay" value="90"/><string name="_hash" value="c522068312bd1dd3e1ac60562fab026b92a1b71b730c1bf6c7d313d05e7da742"/><string name="_outlink" value="Mob/8880831.img/die1/7"/></canvas><canvas name="8" width="1" height="1"><vector name="origin" x="446" y="851"/><int name="z" value="0"/><int name="delay" value="90"/><string name="_hash" value="df0d440f4727e7a631e25e7e0c1b25307b5b5fadb7b27a3f70f077d880c2e802"/><string name="_outlink" value="Mob/8880831.img/die1/8"/></canvas><canvas name="9" width="1" height="1"><vector name="origin" x="474" y="846"/><int name="z" value="0"/><int name="delay" value="90"/><string name="_hash" value="90d10ea28c3ca04b5cc83f10a5560bfa47b38154a2cb32c28e28ac21d48bb6b1"/><string name="_outlink" value="Mob/8880831.img/die1/9"/></canvas><canvas name="10" width="1" height="1"><vector name="origin" x="489" y="849"/><int name="z" value="0"/><int name="delay" value="90"/><string name="_hash" value="61d90806d2568bdfcb96ab760cc8a689ee4287e5f2dcd1f350600a900a5f6843"/><string name="_outlink" value="Mob/8880831.img/die1/10"/></canvas><canvas name="11" width="1" height="1"><vector name="origin" x="493" y="844"/><int name="z" value="0"/><int name="delay" value="90"/><string name="_hash" value="4909703a96a1b522aeb4a83ff724cce9f96af6aa4530d5278dc9cc8ca9f66bfe"/><string name="_outlink" value="Mob/8880831.img/die1/11"/></canvas><canvas name="12" width="1" height="1"><vector name="origin" x="476" y="834"/><int name="z" value="0"/><int name="delay" value="90"/><string name="_hash" value="08df1740b24392ab858527212ca460d7ca0ba1ae3b48ebe702e5bd6b2eec75bb"/><string name="_outlink" value="Mob/8880831.img/die1/12"/></canvas><canvas name="13" width="1" height="1"><vector name="origin" x="464" y="829"/><int name="z" value="0"/><int name="delay" value="90"/><string name="_hash" value="d10d5ea608a70af2c117cce5045ec71e2a3ba03963f6be1592ad333282132a3f"/><string name="_outlink" value="Mob/8880831.img/die1/13"/></canvas><canvas name="14" width="1" height="1"><vector name="origin" x="490" y="836"/><int name="z" value="0"/><int name="delay" value="90"/><string name="_hash" value="8bc93fdc6effee14439c218d7840b1fdf8a1d797b6922f43c4e5ebdf82e59f29"/><string name="_outlink" value="Mob/8880831.img/die1/14"/></canvas><canvas name="15" width="1" height="1"><vector name="origin" x="513" y="841"/><int name="z" value="0"/><int name="delay" value="90"/><string name="_hash" value="22a2a9ca49a7a74548716ca59fba79d4f48704014c302958090bab5c192d005b"/><string name="_outlink" value="Mob/8880831.img/die1/15"/></canvas><canvas name="16" width="1" height="1"><vector name="origin" x="539" y="847"/><int name="z" value="0"/><int name="delay" value="90"/><string name="_hash" value="6ce2c1e1ee1098584b15966fd428fe9ab92cdfaf7b95c092f7af93a9e3a51265"/><string name="_outlink" value="Mob/8880831.img/die1/16"/></canvas><canvas name="17" width="1" height="1"><vector name="origin" x="577" y="856"/><int name="z" value="0"/><int name="delay" value="90"/><string name="_hash" value="124f174ce1dd410251cc0164f456bba582cd257d6db42087709519a62768b569"/><string name="_outlink" value="Mob/8880831.img/die1/17"/></canvas><canvas name="18" width="1" height="1"><vector name="origin" x="621" y="858"/><int name="z" value="0"/><int name="delay" value="90"/><string name="_hash" value="ad7ab53bff427bf7efce033aa0ab6e93dba8add2094e10cf9f057b68abbda6c2"/><string name="_outlink" value="Mob/8880831.img/die1/18"/></canvas><canvas name="19" width="1" height="1"><vector name="origin" x="656" y="864"/><int name="z" value="0"/><int name="delay" value="90"/><string name="_hash" value="9904a18475bfd50d44c20f23bc7849f7614c82db7f498bba0d07e1fa46aed98f"/><string name="_outlink" value="Mob/8880831.img/die1/19"/></canvas><canvas name="20" width="1" height="1"><vector name="origin" x="682" y="885"/><int name="z" value="0"/><int name="delay" value="90"/><string name="_hash" value="71a248910b7acbc3da84e489f9fbe3c63c7dbd086bb7e71167cc9da2480f601c"/><string name="_outlink" value="Mob/8880831.img/die1/20"/></canvas><canvas name="21" width="1" height="1"><vector name="origin" x="702" y="869"/><int name="z" value="0"/><int name="delay" value="90"/><string name="_hash" value="cc5554167bffe4d0ee977f13d66d0e54e86b88140d2f5396702c6c18b8fbef62"/><string name="_outlink" value="Mob/8880831.img/die1/21"/></canvas><canvas name="22" width="1" height="1"><vector name="origin" x="717" y="876"/><int name="z" value="0"/><int name="delay" value="90"/><string name="_hash" value="91429ccaee5e30ca617e8460f177406bd40e82cf4b00caf66acde67596b9f0c1"/><string name="_outlink" value="Mob/8880831.img/die1/22"/></canvas><canvas name="23" width="1" height="1"><vector name="origin" x="730" y="882"/><int name="z" value="0"/><int name="delay" value="90"/><string name="_hash" value="944c1bd9d4f9d3d60032b9ca551aa87e39a18ac1589d841aa5da74c91d9f6348"/><string name="_outlink" value="Mob/8880831.img/die1/23"/></canvas><canvas name="24" width="1" height="1"><vector name="origin" x="739" y="885"/><int name="z" value="0"/><int name="delay" value="90"/><string name="_hash" value="fea6aff3cd64a1f428098fb2102733f39ad6a2fcb2ee719c184bd36181f27c2b"/><string name="_outlink" value="Mob/8880831.img/die1/24"/></canvas><canvas name="25" width="1" height="1"><vector name="origin" x="458" y="877"/><int name="z" value="0"/><int name="delay" value="90"/><string name="_hash" value="68c536f9ad2040d7ceae2c9499e8d16e092145baef5406bc06cd846f1ad89bf7"/><string name="_outlink" value="Mob/8880831.img/die1/25"/></canvas><canvas name="26" width="1" height="1"><vector name="origin" x="466" y="885"/><int name="z" value="0"/><int name="delay" value="90"/><string name="_hash" value="fedfa49b0b40197cc6208e858849a238a640099ab28ffa5bb345132449f48aaf"/><string name="_outlink" value="Mob/8880831.img/die1/26"/></canvas><canvas name="27" width="1" height="1"><vector name="origin" x="413" y="891"/><int name="z" value="0"/><int name="delay" value="90"/><string name="_hash" value="2862252d221e56794ebba97f24702ab992e2e7f89fbf66ee520fe90a8187826c"/><string name="_outlink" value="Mob/8880831.img/die1/27"/></canvas></imgdir><imgdir name="attack1"><imgdir name="info"><imgdir name="range"><vector name="lt" x="-1788" y="-294"/><vector name="rb" x="18" y="33"/></imgdir><imgdir name="hit"><canvas name="0" width="1" height="1"><vector name="origin" x="81" y="85"/><int name="z" value="0"/><int name="delay" value="90"/><string name="_hash" value="110adb7e4ad0b3dfa79c4014954df2de564d5322a950f656056128b18148170e"/><string name="_outlink" value="Mob/8880831.img/attack1/info/hit/0"/></canvas><canvas name="1" width="1" height="1"><vector name="origin" x="99" y="100"/><int name="z" value="0"/><int name="delay" value="90"/><string name="_hash" value="673179b5d0f063e6b8be853685944de2c7c46cd11f9be79e307cbb42af06b6da"/><string name="_outlink" value="Mob/8880831.img/attack1/info/hit/1"/></canvas><canvas name="2" width="1" height="1"><vector name="origin" x="106" y="104"/><int name="z" value="0"/><int name="delay" value="90"/><string name="_hash" value="77c95c9127b4d8236a5a494434652e28596ca63e31ff9b7a32d7305ccac9eca8"/><string name="_outlink" value="Mob/8880831.img/attack1/info/hit/2"/></canvas><canvas name="3" width="1" height="1"><vector name="origin" x="106" y="106"/><int name="z" value="0"/><int name="delay" value="90"/><string name="_hash" value="d8481b75bef8b7140a8972442151a3305cdb7a99daa045ebf654c8804850ffa0"/><string name="_outlink" value="Mob/8880831.img/attack1/info/hit/3"/></canvas><canvas name="4" width="1" height="1"><vector name="origin" x="106" y="107"/><int name="z" value="0"/><int name="delay" value="90"/><string name="_hash" value="0ab953d1959c2b9f11638b7616168e6a89f95846e87e02961dd98abc23f83cc1"/><string name="_outlink" value="Mob/8880831.img/attack1/info/hit/4"/></canvas><canvas name="5" width="1" height="1"><vector name="origin" x="102" y="109"/><int name="z" value="0"/><int name="delay" value="90"/><string name="_hash" value="996cd15ab7148f57920437e8e60f9e9bf259fda4332da208e914e99e9c9b4a3f"/><string name="_outlink" value="Mob/8880831.img/attack1/info/hit/5"/></canvas><canvas name="6" width="1" height="1"><vector name="origin" x="103" y="110"/><int name="z" value="0"/><int name="delay" value="90"/><string name="_hash" value="030a55408e8a6167ee6eac43f28b029e9cfa16f91541cc0c3b6ab47340423527"/><string name="_outlink" value="Mob/8880831.img/attack1/info/hit/6"/></canvas><canvas name="7" width="1" height="1"><vector name="origin" x="105" y="110"/><int name="z" value="0"/><int name="delay" value="90"/><string name="_hash" value="72eae99c33fc87095521db0a935c0f890218b0f9d04e30c544020127b224bf4f"/><string name="_outlink" value="Mob/8880831.img/attack1/info/hit/7"/></canvas><canvas name="8" width="1" height="1"><vector name="origin" x="102" y="113"/><int name="z" value="0"/><int name="delay" value="90"/><string name="_hash" value="5df87faa5896cb64f6a677c759bb4b7d9b6c1878910e2635023034d38f981eb2"/><string name="_outlink" value="Mob/8880831.img/attack1/info/hit/8"/></canvas></imgdir><int name="attackAfter" value="1530"/></imgdir><canvas name="0" width="1" height="1"><vector name="origin" x="343" y="655"/><int name="z" value="0"/><int name="delay" value="90"/><vector name="lt" x="-183" y="-408"/><vector name="rb" x="180" y="7"/><vector name="head" x="-75" y="-333"/><string name="_hash" value="ebc3e5efc6681911ca4e9bb957bec5fa055ea93252bd9263291b60b82c8c8737"/><string name="_outlink" value="Mob/8880831.img/attack1/0"/></canvas><canvas name="1" width="1" height="1"><vector name="origin" x="353" y="684"/><int name="z" value="0"/><int name="delay" value="90"/><vector name="lt" x="-183" y="-408"/><vector name="rb" x="180" y="7"/><vector name="head" x="-75" y="-333"/><string name="_hash" value="7ed259cd2729f1176fd6ef84bd0fba2b3e5f4ceafe4b92dcfb6bd8d0838bf050"/><string name="_outlink" value="Mob/8880831.img/attack1/1"/></canvas><canvas name="2" width="1" height="1"><vector name="origin" x="366" y="713"/><int name="z" value="0"/><int name="delay" value="90"/><vector name="lt" x="-183" y="-408"/><vector name="rb" x="180" y="7"/><vector name="head" x="-75" y="-333"/><string name="_hash" value="755481c0b0598787239d72e319a6f0d42f7565b80ad0cb65209389dabca5b814"/><string name="_outlink" value="Mob/8880831.img/attack1/2"/></canvas><canvas name="3" width="1" height="1"><vector name="origin" x="382" y="740"/><int name="z" value="0"/><int name="delay" value="90"/><vector name="lt" x="-183" y="-408"/><vector name="rb" x="180" y="7"/><vector name="head" x="-75" y="-333"/><string name="_hash" value="9277a00b87d27be71b763918f5c17b718cd63f8903866a28c25cf791e023e76a"/><string name="_outlink" value="Mob/8880831.img/attack1/3"/></canvas><canvas name="4" width="1" height="1"><vector name="origin" x="462" y="765"/><int name="z" value="0"/><int name="delay" value="90"/><vector name="lt" x="-183" y="-408"/><vector name="rb" x="180" y="7"/><vector name="head" x="-75" y="-333"/><string name="_hash" value="d1593192a073687e1fde6c37408d4b3580b45affa1f030c175fca258a1f48102"/><string name="_outlink" value="Mob/8880831.img/attack1/4"/></canvas><canvas name="5" width="1" height="1"><vector name="origin" x="1783" y="959"/><int name="z" value="0"/><int name="delay" value="90"/><vector name="lt" x="-183" y="-408"/><vector name="rb" x="180" y="7"/><vector name="head" x="-75" y="-333"/><string name="_hash" value="afca3db8a5f2ef1a3e37198484e9e89ea99bed761d09ab1857d96371c25e8bd0"/><string name="_outlink" value="Mob/8880831.img/attack1/5"/></canvas><canvas name="6" width="1" height="1"><vector name="origin" x="1832" y="967"/><int name="z" value="0"/><int name="delay" value="90"/><vector name="lt" x="-183" y="-408"/><vector name="rb" x="180" y="7"/><vector name="head" x="-75" y="-333"/><string name="_hash" value="20aa315e84d6226760e22f6616a55b19a2d39f63153d8399e064f32355e3a1da"/><string name="_outlink" value="Mob/8880831.img/attack1/6"/></canvas><canvas name="7" width="1" height="1"><vector name="origin" x="1843" y="1010"/><int name="z" value="0"/><int name="delay" value="90"/><vector name="lt" x="-183" y="-408"/><vector name="rb" x="180" y="7"/><vector name="head" x="-75" y="-333"/><string name="_hash" value="23dfa018c10dd8a0fe8c4ead8f5a83dc7fb4c2031f39f5f0cfdbf9a5c5c3e87b"/><string name="_outlink" value="Mob/8880831.img/attack1/7"/></canvas><canvas name="8" width="1" height="1"><vector name="origin" x="1854" y="1051"/><int name="z" value="0"/><int name="delay" value="90"/><vector name="lt" x="-183" y="-408"/><vector name="rb" x="180" y="7"/><vector name="head" x="-75" y="-333"/><string name="_hash" value="3b4b550de6cdbcdd3da88a364ef24b7b24ca84d251786c93187962fd3d06d2c3"/><string name="_outlink" value="Mob/8880831.img/attack1/8"/></canvas><canvas name="9" width="1" height="1"><vector name="origin" x="1865" y="1078"/><int name="z" value="0"/><int name="delay" value="90"/><vector name="lt" x="-183" y="-408"/><vector name="rb" x="180" y="7"/><vector name="head" x="-75" y="-333"/><string name="_hash" value="652990a26805d295d8e5de7f0860dc01bd1fb2a1fc6a2f6b4a0ea24b755e7a9f"/><string name="_outlink" value="Mob/8880831.img/attack1/9"/></canvas><canvas name="10" width="1" height="1"><vector name="origin" x="1879" y="1125"/><int name="z" value="0"/><int name="delay" value="90"/><vector name="lt" x="-183" y="-408"/><vector name="rb" x="180" y="7"/><vector name="head" x="-75" y="-333"/><string name="_hash" value="517c097203ebafe06b9a1d449503381e84e00fc4629cacc46b59c051adad43fb"/><string name="_outlink" value="Mob/8880831.img/attack1/10"/></canvas><canvas name="11" width="1" height="1"><vector name="origin" x="1887" y="1130"/><int name="z" value="0"/><int name="delay" value="90"/><vector name="lt" x="-183" y="-408"/><vector name="rb" x="180" y="7"/><vector name="head" x="-75" y="-333"/><string name="_hash" value="6070b0c65bdc9837eb784eb050e072cb0059e12ee29a5e40149f6b333367ea8f"/><string name="_outlink" value="Mob/8880831.img/attack1/11"/></canvas><canvas name="12" width="1" height="1"><vector name="origin" x="1879" y="1130"/><int name="z" value="0"/><int name="delay" value="90"/><vector name="lt" x="-183" y="-408"/><vector name="rb" x="180" y="7"/><vector name="head" x="-75" y="-333"/><string name="_hash" value="5700a285253ec82094ee5d2a012310394d0082d599c406abfb6ab35594a0a315"/><string name="_outlink" value="Mob/8880831.img/attack1/12"/></canvas><canvas name="13" width="1" height="1"><vector name="origin" x="1879" y="1130"/><int name="z" value="0"/><int name="delay" value="90"/><vector name="lt" x="-183" y="-408"/><vector name="rb" x="180" y="7"/><vector name="head" x="-75" y="-333"/><string name="_hash" value="ac564a986e60ed05523700c1104addc39887a5e07c333aa27a14b70c19af77c1"/><string name="_outlink" value="Mob/8880831.img/attack1/13"/></canvas><canvas name="14" width="1" height="1"><vector name="origin" x="1884" y="1130"/><int name="z" value="0"/><int name="delay" value="90"/><vector name="lt" x="-183" y="-408"/><vector name="rb" x="180" y="7"/><vector name="head" x="-75" y="-333"/><string name="_hash" value="261a47c83390251803b0e68799294e36d2b8371d0dfe4165f8d2a79c483db4c3"/><string name="_outlink" value="Mob/8880831.img/attack1/14"/></canvas><canvas name="15" width="1" height="1"><vector name="origin" x="1887" y="1130"/><int name="z" value="0"/><int name="delay" value="90"/><vector name="lt" x="-183" y="-408"/><vector name="rb" x="180" y="7"/><vector name="head" x="-75" y="-333"/><string name="_hash" value="3a0ab3e389c0d3fe09c90d55e56777ae20133d5bad4d0732737bd05806153a52"/><string name="_outlink" value="Mob/8880831.img/attack1/15"/></canvas><canvas name="16" width="1" height="1"><vector name="origin" x="1820" y="1130"/><int name="z" value="0"/><int name="delay" value="90"/><vector name="lt" x="-183" y="-408"/><vector name="rb" x="180" y="7"/><vector name="head" x="-75" y="-333"/><string name="_hash" value="573cc22f2b20db287ad69ce3b00ca3512d4d9c52e5d548a0890d0262dc854d28"/><string name="_outlink" value="Mob/8880831.img/attack1/16"/></canvas><canvas name="17" width="1" height="1"><vector name="origin" x="1987" y="841"/><int name="z" value="0"/><int name="delay" value="90"/><vector name="lt" x="-183" y="-408"/><vector name="rb" x="180" y="7"/><vector name="head" x="-75" y="-333"/><string name="_hash" value="d7d0ca09df22622c484de12620c8f498d3f7b1756292d4a416a14e2d3171504f"/><string name="_outlink" value="Mob/8880831.img/attack1/17"/></canvas><canvas name="18" width="1" height="1"><vector name="origin" x="1990" y="832"/><int name="z" value="0"/><int name="delay" value="90"/><vector name="lt" x="-183" y="-408"/><vector name="rb" x="180" y="7"/><vector name="head" x="-75" y="-333"/><string name="_hash" value="8b572678dffa25080bf65507d55cce0ed94cb691fcb022fe9c967fc0ae214101"/><string name="_outlink" value="Mob/8880831.img/attack1/18"/></canvas><canvas name="19" width="1" height="1"><vector name="origin" x="1982" y="822"/><int name="z" value="0"/><int name="delay" value="90"/><vector name="lt" x="-183" y="-408"/><vector name="rb" x="180" y="7"/><vector name="head" x="-75" y="-333"/><string name="_hash" value="5f5ebbe709341f207abd5938917c2765340b63a4aa793edccedab6659701b3ac"/><string name="_outlink" value="Mob/8880831.img/attack1/19"/></canvas><canvas name="20" width="1" height="1"><vector name="origin" x="1978" y="806"/><int name="z" value="0"/><int name="delay" value="90"/><vector name="lt" x="-183" y="-408"/><vector name="rb" x="180" y="7"/><vector name="head" x="-75" y="-333"/><string name="_hash" value="ff23aabeb03ba61f8ff7ab121ef9615c21f9a44b59c88b224d76185607a5b909"/><string name="_outlink" value="Mob/8880831.img/attack1/20"/></canvas><canvas name="21" width="1" height="1"><vector name="origin" x="1971" y="787"/><int name="z" value="0"/><int name="delay" value="90"/><vector name="lt" x="-183" y="-408"/><vector name="rb" x="180" y="7"/><vector name="head" x="-75" y="-333"/><string name="_hash" value="2b2cda73a0536603b6c31cc6eb410f484ddb1eebfd406030d8604842b63b0389"/><string name="_outlink" value="Mob/8880831.img/attack1/21"/></canvas><canvas name="22" width="1" height="1"><vector name="origin" x="1959" y="724"/><int name="z" value="0"/><int name="delay" value="90"/><vector name="lt" x="-183" y="-408"/><vector name="rb" x="180" y="7"/><vector name="head" x="-75" y="-333"/><string name="_hash" value="e234a0edf945266495e1edd05677042da181252999496116dd1422b4977031be"/><string name="_outlink" value="Mob/8880831.img/attack1/22"/></canvas><canvas name="23" width="1" height="1"><vector name="origin" x="1960" y="602"/><int name="z" value="0"/><int name="delay" value="90"/><vector name="lt" x="-183" y="-408"/><vector name="rb" x="180" y="7"/><vector name="head" x="-75" y="-333"/><string name="_hash" value="b00ff344333666a3235a52fb00a3dc81ff53adea33d9717324d0eecd2d70012a"/><string name="_outlink" value="Mob/8880831.img/attack1/23"/></canvas><canvas name="24" width="1" height="1"><vector name="origin" x="1961" y="601"/><int name="z" value="0"/><int name="delay" value="90"/><vector name="lt" x="-183" y="-408"/><vector name="rb" x="180" y="7"/><vector name="head" x="-75" y="-333"/><string name="_hash" value="9bbde78af693c5248b17a01b26b12e0b4c2be17f5655d61137be5dc6ebc0471a"/><string name="_outlink" value="Mob/8880831.img/attack1/24"/></canvas><canvas name="25" width="1" height="1"><vector name="origin" x="1892" y="602"/><int name="z" value="0"/><int name="delay" value="90"/><vector name="lt" x="-183" y="-408"/><vector name="rb" x="180" y="7"/><vector name="head" x="-75" y="-333"/><string name="_hash" value="17f7ee5190b245f8d7884b57e34733b8571703cc1876de197b936fb509ea9d52"/><string name="_outlink" value="Mob/8880831.img/attack1/25"/></canvas><canvas name="26" width="1" height="1"><vector name="origin" x="1884" y="591"/><int name="z" value="0"/><int name="delay" value="90"/><vector name="lt" x="-183" y="-408"/><vector name="rb" x="180" y="7"/><vector name="head" x="-75" y="-333"/><string name="_hash" value="47f8eb785bec480f1f5a32a0e22c9719e144e8cce713305c2064a8504c57562a"/><string name="_outlink" value="Mob/8880831.img/attack1/26"/></canvas><canvas name="27" width="1" height="1"><vector name="origin" x="1822" y="550"/><int name="z" value="0"/><int name="delay" value="90"/><vector name="lt" x="-183" y="-408"/><vector name="rb" x="180" y="7"/><vector name="head" x="-75" y="-333"/><string name="_hash" value="755e2f2a155675ac71f69f06a06fe23f1609412e4dace2d395ffa19b51b15ef0"/><string name="_outlink" value="Mob/8880831.img/attack1/27"/></canvas><canvas name="28" width="1" height="1"><vector name="origin" x="1811" y="626"/><int name="z" value="0"/><int name="delay" value="90"/><vector name="lt" x="-183" y="-408"/><vector name="rb" x="180" y="7"/><vector name="head" x="-75" y="-333"/><string name="_hash" value="4acdbddc9d43fb8f00630e0e0b043684c2d2a49665aebed785f0db1b511002b5"/><string name="_outlink" value="Mob/8880831.img/attack1/28"/></canvas></imgdir><imgdir name="attack2"><imgdir name="info"><imgdir name="range"><vector name="lt" x="-606" y="-588"/><vector name="rb" x="-78" y="-24"/></imgdir><imgdir name="hit"><canvas name="0" width="1" height="1"><vector name="origin" x="102" y="70"/><int name="z" value="0"/><int name="delay" value="60"/><string name="_hash" value="bd1a8f8a0225b557814c0fddf633742f98db9974e8900e126254cbaccb95687f"/><string name="_outlink" value="Mob/8880831.img/attack2/info/hit/0"/></canvas><canvas name="1" width="1" height="1"><vector name="origin" x="85" y="102"/><int name="z" value="0"/><int name="delay" value="60"/><string name="_hash" value="50ccc7cb948b38c97c76cf6729c8932941421b992a66aaabedc0944541624f6b"/><string name="_outlink" value="Mob/8880831.img/attack2/info/hit/1"/></canvas><canvas name="2" width="1" height="1"><vector name="origin" x="105" y="111"/><int name="z" value="0"/><int name="delay" value="60"/><string name="_hash" value="466b64164f34282a625dfe5599fb33644601a882d7f4e8166886cbb84cfe9b94"/><string name="_outlink" value="Mob/8880831.img/attack2/info/hit/2"/></canvas><canvas name="3" width="1" height="1"><vector name="origin" x="114" y="121"/><int name="z" value="0"/><int name="delay" value="60"/><string name="_hash" value="78adf809505c4709b955b5230bb1bd723be48640805c5967d3e6ef3479f66b16"/><string name="_outlink" value="Mob/8880831.img/attack2/info/hit/3"/></canvas><canvas name="4" width="1" height="1"><vector name="origin" x="112" y="121"/><int name="z" value="0"/><int name="delay" value="60"/><string name="_hash" value="8d38a3d84f9f4fdb0ab252acdce04c2376bc388ff2a22193c39b42e1d1786c36"/><string name="_outlink" value="Mob/8880831.img/attack2/info/hit/4"/></canvas><canvas name="5" width="1" height="1"><vector name="origin" x="108" y="117"/><int name="z" value="0"/><int name="delay" value="60"/><string name="_hash" value="00bf8672d4dbc45d9f7c13c3dc611c6be5bf1333eaf61cbd65a6139d625ba1ce"/><string name="_outlink" value="Mob/8880831.img/attack2/info/hit/5"/></canvas><canvas name="6" width="1" height="1"><vector name="origin" x="109" y="115"/><int name="z" value="0"/><int name="delay" value="60"/><string name="_hash" value="6bd8297fc25c1271de71a63fc4b03dd95178169d9f82d3f0b5945d1bf737276e"/><string name="_outlink" value="Mob/8880831.img/attack2/info/hit/6"/></canvas><canvas name="7" width="1" height="1"><vector name="origin" x="111" y="113"/><int name="z" value="0"/><int name="delay" value="60"/><string name="_hash" value="87c1a2dfe5f7626794fcb57a2dfd2c772044fbe134cc7241b28cc0789d23378a"/><string name="_outlink" value="Mob/8880831.img/attack2/info/hit/7"/></canvas></imgdir><int name="attackAfter" value="720"/></imgdir><canvas name="0" width="1" height="1"><vector name="origin" x="393" y="519"/><int name="z" value="0"/><int name="delay" value="90"/><vector name="lt" x="-183" y="-408"/><vector name="rb" x="180" y="7"/><vector name="head" x="-75" y="-333"/><string name="_hash" value="e04c234ee6845e570868757ef53be1b0ea023b92f75e57d7740f20edc1dce241"/><string name="_outlink" value="Mob/8880831.img/attack2/0"/></canvas><canvas name="1" width="1" height="1"><vector name="origin" x="709" y="700"/><int name="z" value="0"/><int name="delay" value="90"/><vector name="lt" x="-183" y="-408"/><vector name="rb" x="180" y="7"/><vector name="head" x="-75" y="-333"/><string name="_hash" value="3a5217f7540e35d78f2c1e55e10ea20de3c1e20cb3088514d3294251be149908"/><string name="_outlink" value="Mob/8880831.img/attack2/1"/></canvas><canvas name="2" width="1" height="1"><vector name="origin" x="718" y="701"/><int name="z" value="0"/><int name="delay" value="90"/><vector name="lt" x="-183" y="-408"/><vector name="rb" x="180" y="7"/><vector name="head" x="-75" y="-333"/><string name="_hash" value="09d30755b55c141f5c9a2871dc948371c60f75cac7822b4ed0769a029d8a53cc"/><string name="_outlink" value="Mob/8880831.img/attack2/2"/></canvas><canvas name="3" width="1" height="1"><vector name="origin" x="734" y="706"/><int name="z" value="0"/><int name="delay" value="90"/><vector name="lt" x="-183" y="-408"/><vector name="rb" x="180" y="7"/><vector name="head" x="-75" y="-333"/><string name="_hash" value="30ee39e2bfac48c7f81568d0059fc71a7525685db2390cbe0aefad71fa8d24d4"/><string name="_outlink" value="Mob/8880831.img/attack2/3"/></canvas><canvas name="4" width="1" height="1"><vector name="origin" x="741" y="705"/><int name="z" value="0"/><int name="delay" value="90"/><vector name="lt" x="-183" y="-408"/><vector name="rb" x="180" y="7"/><vector name="head" x="-75" y="-333"/><string name="_hash" value="bcb17060765273d3ce20d2be207974f0720772b7c087006f825a1aa85c51aa8f"/><string name="_outlink" value="Mob/8880831.img/attack2/4"/></canvas><canvas name="5" width="1" height="1"><vector name="origin" x="741" y="706"/><int name="z" value="0"/><int name="delay" value="90"/><vector name="lt" x="-183" y="-408"/><vector name="rb" x="180" y="7"/><vector name="head" x="-75" y="-333"/><string name="_hash" value="7d1dcc093053863eaec3d59bfe3096c736abcdaa30d9480974d733949dc8a118"/><string name="_outlink" value="Mob/8880831.img/attack2/5"/></canvas><canvas name="6" width="1" height="1"><vector name="origin" x="742" y="708"/><int name="z" value="0"/><int name="delay" value="90"/><vector name="lt" x="-183" y="-408"/><vector name="rb" x="180" y="7"/><vector name="head" x="-75" y="-333"/><string name="_hash" value="d901782719da93e525765557ae1a38436b8022f837acba6c757ef3a12f5f5527"/><string name="_outlink" value="Mob/8880831.img/attack2/6"/></canvas><canvas name="7" width="1" height="1"><vector name="origin" x="741" y="709"/><int name="z" value="0"/><int name="delay" value="90"/><vector name="lt" x="-183" y="-408"/><vector name="rb" x="180" y="7"/><vector name="head" x="-75" y="-333"/><string name="_hash" value="b6b2f930f3f498ee0c186db956667d3d1db96d27091834b68c8fdad3a34e4f5d"/><string name="_outlink" value="Mob/8880831.img/attack2/7"/></canvas><canvas name="8" width="1" height="1"><vector name="origin" x="782" y="708"/><int name="z" value="0"/><int name="delay" value="60"/><vector name="lt" x="-183" y="-408"/><vector name="rb" x="180" y="7"/><vector name="head" x="-75" y="-333"/><string name="_hash" value="1f8161acf767127db00b7a1581493cd9f905eadf88fae84fec46621bfe859b9a"/><string name="_outlink" value="Mob/8880831.img/attack2/8"/></canvas><canvas name="9" width="1" height="1"><vector name="origin" x="814" y="788"/><int name="z" value="0"/><int name="delay" value="60"/><vector name="lt" x="-183" y="-408"/><vector name="rb" x="180" y="7"/><vector name="head" x="-75" y="-333"/><string name="_hash" value="48505824bccd1ee7e7fa2fd53a32285b8ba6401b1cf89505b603dbc8a425af4f"/><string name="_outlink" value="Mob/8880831.img/attack2/9"/></canvas><canvas name="10" width="1" height="1"><vector name="origin" x="803" y="815"/><int name="z" value="0"/><int name="delay" value="60"/><vector name="lt" x="-183" y="-408"/><vector name="rb" x="180" y="7"/><vector name="head" x="-75" y="-333"/><string name="_hash" value="dc29a163290745261b859436237ad38c9ec3b9350b5375ba24cb5408b479a7e4"/><string name="_outlink" value="Mob/8880831.img/attack2/10"/></canvas><canvas name="11" width="1" height="1"><vector name="origin" x="824" y="767"/><int name="z" value="0"/><int name="delay" value="60"/><vector name="lt" x="-183" y="-408"/><vector name="rb" x="180" y="7"/><vector name="head" x="-75" y="-333"/><string name="_hash" value="4a46baef082198eda3eb594e6ba3f1457c386b8acb81725f1c152b27d6fd9879"/><string name="_outlink" value="Mob/8880831.img/attack2/11"/></canvas><canvas name="12" width="1" height="1"><vector name="origin" x="822" y="803"/><int name="z" value="0"/><int name="delay" value="60"/><vector name="lt" x="-183" y="-408"/><vector name="rb" x="180" y="7"/><vector name="head" x="-75" y="-333"/><string name="_hash" value="1fe765c471f61babc21532598b8f59d77df11ca14ac0934f18147ed0e8e3f1ec"/><string name="_outlink" value="Mob/8880831.img/attack2/12"/></canvas><canvas name="13" width="1" height="1"><vector name="origin" x="738" y="791"/><int name="z" value="0"/><int name="delay" value="60"/><vector name="lt" x="-183" y="-408"/><vector name="rb" x="180" y="7"/><vector name="head" x="-75" y="-333"/><string name="_hash" value="47ee17a400148e8f8efe15f62076aac13b9f7701ea00f9286bf5db4825b207f6"/><string name="_outlink" value="Mob/8880831.img/attack2/13"/></canvas><canvas name="14" width="1" height="1"><vector name="origin" x="743" y="805"/><int name="z" value="0"/><int name="delay" value="60"/><vector name="lt" x="-183" y="-408"/><vector name="rb" x="180" y="7"/><vector name="head" x="-75" y="-333"/><string name="_hash" value="168f902c25c210c7459be3cc11ca7de10b1f4601a789127977ac8aa41263e565"/><string name="_outlink" value="Mob/8880831.img/attack2/14"/></canvas><canvas name="15" width="1" height="1"><vector name="origin" x="749" y="809"/><int name="z" value="0"/><int name="delay" value="60"/><vector name="lt" x="-183" y="-408"/><vector name="rb" x="180" y="7"/><vector name="head" x="-75" y="-333"/><string name="_hash" value="1ce40f5e1851eb78d32460cc5493deb7b8e3d5ba62b69fb8407b6928b7ab1bd5"/><string name="_outlink" value="Mob/8880831.img/attack2/15"/></canvas><canvas name="16" width="1" height="1"><vector name="origin" x="760" y="811"/><int name="z" value="0"/><int name="delay" value="60"/><vector name="lt" x="-183" y="-408"/><vector name="rb" x="180" y="7"/><vector name="head" x="-75" y="-333"/><string name="_hash" value="eda5e14c05014a12edbde9c16adc16c9be403b6fce63dea36211c1f24c8d3f76"/><string name="_outlink" value="Mob/8880831.img/attack2/16"/></canvas><canvas name="17" width="1" height="1"><vector name="origin" x="771" y="769"/><int name="z" value="0"/><int name="delay" value="60"/><vector name="lt" x="-183" y="-408"/><vector name="rb" x="180" y="7"/><vector name="head" x="-75" y="-333"/><string name="_hash" value="ce5966634dabade5134b1e45fc8361f6113a4201d122cffe9cd7f5b6cb20f62d"/><string name="_outlink" value="Mob/8880831.img/attack2/17"/></canvas><canvas name="18" width="1" height="1"><vector name="origin" x="779" y="770"/><int name="z" value="0"/><int name="delay" value="60"/><vector name="lt" x="-183" y="-408"/><vector name="rb" x="180" y="7"/><vector name="head" x="-75" y="-333"/><string name="_hash" value="8dfdf5c7d26419075bb57c6510aced4a4817b7759b386c199b525c8b4b3adfd1"/><string name="_outlink" value="Mob/8880831.img/attack2/18"/></canvas><canvas name="19" width="1" height="1"><vector name="origin" x="773" y="771"/><int name="z" value="0"/><int name="delay" value="60"/><vector name="lt" x="-183" y="-408"/><vector name="rb" x="180" y="7"/><vector name="head" x="-75" y="-333"/><string name="_hash" value="3bc8243f641631a97b452a06d24d4907df83a49e9ff4f18a763598ddfb205e7a"/><string name="_outlink" value="Mob/8880831.img/attack2/19"/></canvas><canvas name="20" width="1" height="1"><vector name="origin" x="764" y="744"/><int name="z" value="0"/><int name="delay" value="60"/><vector name="lt" x="-183" y="-408"/><vector name="rb" x="180" y="7"/><vector name="head" x="-75" y="-333"/><string name="_hash" value="fb14f48d8635b17664bbf3f3e0a964f38dcb68fd92e7e3535dfc16da9c37f07f"/><string name="_outlink" value="Mob/8880831.img/attack2/20"/></canvas><canvas name="21" width="1" height="1"><vector name="origin" x="710" y="740"/><int name="z" value="0"/><int name="delay" value="60"/><vector name="lt" x="-183" y="-408"/><vector name="rb" x="180" y="7"/><vector name="head" x="-75" y="-333"/><string name="_hash" value="599487a39548c629c7419fa8b767621c31b0247b4ad37a594a492b2f1311bf1d"/><string name="_outlink" value="Mob/8880831.img/attack2/21"/></canvas><canvas name="22" width="1" height="1"><vector name="origin" x="703" y="720"/><int name="z" value="0"/><int name="delay" value="60"/><vector name="lt" x="-183" y="-408"/><vector name="rb" x="180" y="7"/><vector name="head" x="-75" y="-333"/><string name="_hash" value="279f825334e27b09dcc5777e14edf43e97b9a315a3aca69c61fd1d32424cecb0"/><string name="_outlink" value="Mob/8880831.img/attack2/22"/></canvas><canvas name="23" width="1" height="1"><vector name="origin" x="689" y="691"/><int name="z" value="0"/><int name="delay" value="60"/><vector name="lt" x="-183" y="-408"/><vector name="rb" x="180" y="7"/><vector name="head" x="-75" y="-333"/><string name="_hash" value="20adf30f600a174ffadabb98a501c00ef19dd7d5533ec944a94190ff0f08116a"/><string name="_outlink" value="Mob/8880831.img/attack2/23"/></canvas><canvas name="24" width="1" height="1"><vector name="origin" x="393" y="515"/><int name="z" value="0"/><int name="delay" value="60"/><vector name="lt" x="-183" y="-408"/><vector name="rb" x="180" y="7"/><vector name="head" x="-75" y="-333"/><string name="_hash" value="32f1692a979d8a0ff79232c352d93c3ffdabc69cf6913235272ceb2e3aa85b3d"/><string name="_outlink" value="Mob/8880831.img/attack2/24"/></canvas></imgdir><imgdir name="attack3"><imgdir name="info"><imgdir name="range"><vector name="lt" x="133" y="-581"/><vector name="rb" x="469" y="16"/></imgdir><imgdir name="hit"><canvas name="0" width="1" height="1"><vector name="origin" x="30" y="50"/><int name="z" value="0"/><int name="delay" value="60"/><string name="_hash" value="da4594c8e8b54b6d04a8413810900002b796e4ff7cb967741ada881453a6b28a"/><string name="_outlink" value="Mob/8880831.img/attack3/info/hit/0"/></canvas><canvas name="1" width="1" height="1"><vector name="origin" x="69" y="85"/><int name="z" value="0"/><int name="delay" value="60"/><string name="_hash" value="2f63c80a600d9db959b70f23db2db9fc798f2d4e07b7afe8be2a695c3bd9e37c"/><string name="_outlink" value="Mob/8880831.img/attack3/info/hit/1"/></canvas><canvas name="2" width="1" height="1"><vector name="origin" x="76" y="87"/><int name="z" value="0"/><int name="delay" value="60"/><string name="_hash" value="4bb80a632df9d3b3b15495af9f9ca0f20545e1a04044dcedd54dc95230b4bb22"/><string name="_outlink" value="Mob/8880831.img/attack3/info/hit/2"/></canvas><canvas name="3" width="1" height="1"><vector name="origin" x="79" y="94"/><int name="z" value="0"/><int name="delay" value="60"/><string name="_hash" value="9a4c0f7818d9e37a3b69b7d4a8cff7d2eb2b56b64bffc17e13af3532f89d705c"/><string name="_outlink" value="Mob/8880831.img/attack3/info/hit/3"/></canvas><canvas name="4" width="1" height="1"><vector name="origin" x="89" y="93"/><int name="z" value="0"/><int name="delay" value="60"/><string name="_hash" value="3b7bf3b7dd1516e0f6781a9416a8a503d205b5ad3303249f4dbcec83956885a2"/><string name="_outlink" value="Mob/8880831.img/attack3/info/hit/4"/></canvas><canvas name="5" width="1" height="1"><vector name="origin" x="93" y="93"/><int name="z" value="0"/><int name="delay" value="60"/><string name="_hash" value="7c7e5d15f9a18e48e79725d8679dab0f23be03fe999c9e29110efc19bcc2acb7"/><string name="_outlink" value="Mob/8880831.img/attack3/info/hit/5"/></canvas><canvas name="6" width="1" height="1"><vector name="origin" x="91" y="90"/><int name="z" value="0"/><int name="delay" value="60"/><string name="_hash" value="25f8717382697a7a5b1136ca05ccb201ae73ad0a68888a814f234399a1b7c5e0"/><string name="_outlink" value="Mob/8880831.img/attack3/info/hit/6"/></canvas><canvas name="7" width="1" height="1"><vector name="origin" x="89" y="96"/><int name="z" value="0"/><int name="delay" value="60"/><string name="_hash" value="e7f678fd627a0a7099806d98d7c8bcfd7293a324b5b4b67067622c27656041e9"/><string name="_outlink" value="Mob/8880831.img/attack3/info/hit/7"/></canvas></imgdir><int name="attackAfter" value="540"/></imgdir><canvas name="0" width="1" height="1"><vector name="origin" x="393" y="530"/><int name="z" value="0"/><int name="delay" value="90"/><vector name="lt" x="-183" y="-408"/><vector name="rb" x="180" y="7"/><vector name="head" x="-75" y="-333"/><string name="_hash" value="3b9dea7b56bfa968943a3043dca2734d646ee43baab635f6dfa8d1a919397103"/><string name="_outlink" value="Mob/8880831.img/attack3/0"/></canvas><canvas name="1" width="1" height="1"><vector name="origin" x="382" y="595"/><int name="z" value="0"/><int name="delay" value="90"/><vector name="lt" x="-183" y="-408"/><vector name="rb" x="180" y="7"/><vector name="head" x="-75" y="-333"/><string name="_hash" value="a438224d8ea83324ed126b5124a1a3e6cb72a9fb0f151ea60609e0c45e975aaf"/><string name="_outlink" value="Mob/8880831.img/attack3/1"/></canvas><canvas name="2" width="1" height="1"><vector name="origin" x="424" y="798"/><int name="z" value="0"/><int name="delay" value="90"/><vector name="lt" x="-183" y="-408"/><vector name="rb" x="180" y="7"/><vector name="head" x="-75" y="-333"/><string name="_hash" value="a3615ffdf2ca899acf4f437e218dd77077af258a7f1263fdc6dc3f9c34165703"/><string name="_outlink" value="Mob/8880831.img/attack3/2"/></canvas><canvas name="3" width="1" height="1"><vector name="origin" x="446" y="823"/><int name="z" value="0"/><int name="delay" value="90"/><vector name="lt" x="-183" y="-408"/><vector name="rb" x="180" y="7"/><vector name="head" x="-75" y="-333"/><string name="_hash" value="1107dcd4e4addc7f45994dac41440931019b6c4e007a510b02937d7fecadc18d"/><string name="_outlink" value="Mob/8880831.img/attack3/3"/></canvas><canvas name="4" width="1" height="1"><vector name="origin" x="454" y="823"/><int name="z" value="0"/><int name="delay" value="90"/><vector name="lt" x="-183" y="-408"/><vector name="rb" x="180" y="7"/><vector name="head" x="-75" y="-333"/><string name="_hash" value="d456622609f86f2cfca29b839d315b6b653355641174600e9e139b3e3226eaaf"/><string name="_outlink" value="Mob/8880831.img/attack3/4"/></canvas><canvas name="5" width="1" height="1"><vector name="origin" x="451" y="789"/><int name="z" value="0"/><int name="delay" value="90"/><vector name="lt" x="-183" y="-408"/><vector name="rb" x="180" y="7"/><vector name="head" x="-75" y="-333"/><string name="_hash" value="0bcf42038d4cc73794015022323b9438cced7b8fdfdd29d8750008c25850784c"/><string name="_outlink" value="Mob/8880831.img/attack3/5"/></canvas><canvas name="6" width="1" height="1"><vector name="origin" x="435" y="789"/><int name="z" value="0"/><int name="delay" value="90"/><vector name="lt" x="-183" y="-408"/><vector name="rb" x="180" y="7"/><vector name="head" x="-75" y="-333"/><string name="_hash" value="d762cf134ae04978faf472628e10062b79dcd8e17dfc06fb700c50ceaf33be48"/><string name="_outlink" value="Mob/8880831.img/attack3/6"/></canvas><canvas name="7" width="1" height="1"><vector name="origin" x="368" y="789"/><int name="z" value="0"/><int name="delay" value="90"/><vector name="lt" x="-183" y="-408"/><vector name="rb" x="180" y="7"/><vector name="head" x="-75" y="-333"/><string name="_hash" value="447ced2925ad8be035c4d7911a4a9a5b0d2844d5465756a7c0b2b9df152cb274"/><string name="_outlink" value="Mob/8880831.img/attack3/7"/></canvas><canvas name="8" width="1" height="1"><vector name="origin" x="370" y="789"/><int name="z" value="0"/><int name="delay" value="90"/><vector name="lt" x="-183" y="-408"/><vector name="rb" x="180" y="7"/><vector name="head" x="-75" y="-333"/><string name="_hash" value="e5d408ac17276821da8782000672f8b1af6ab36ea633ca9d680d00e9eb818a68"/><string name="_outlink" value="Mob/8880831.img/attack3/8"/></canvas><canvas name="9" width="1" height="1"><vector name="origin" x="370" y="789"/><int name="z" value="0"/><int name="delay" value="90"/><vector name="lt" x="-183" y="-408"/><vector name="rb" x="180" y="7"/><vector name="head" x="-75" y="-333"/><string name="_hash" value="e75c0e19a9cf8ea7891dbdd85e588148377d6ed91d44bdda24d22c6742b2b0cd"/><string name="_outlink" value="Mob/8880831.img/attack3/9"/></canvas><canvas name="10" width="1" height="1"><vector name="origin" x="372" y="769"/><int name="z" value="0"/><int name="delay" value="90"/><vector name="lt" x="-183" y="-408"/><vector name="rb" x="180" y="7"/><vector name="head" x="-75" y="-333"/><string name="_hash" value="28b64d2a8632eda1940006cf64a5293ace936178cf995952b867a24a4cc011d8"/><string name="_outlink" value="Mob/8880831.img/attack3/10"/></canvas><canvas name="11" width="1" height="1"><vector name="origin" x="368" y="756"/><int name="z" value="0"/><int name="delay" value="90"/><vector name="lt" x="-183" y="-408"/><vector name="rb" x="180" y="7"/><vector name="head" x="-75" y="-333"/><string name="_hash" value="e48ee4e8602b7ba483bb2b38966be7cac9aeb453fbe3418872c838ca329f5c92"/><string name="_outlink" value="Mob/8880831.img/attack3/11"/></canvas><canvas name="12" width="1" height="1"><vector name="origin" x="369" y="756"/><int name="z" value="0"/><int name="delay" value="90"/><vector name="lt" x="-183" y="-408"/><vector name="rb" x="180" y="7"/><vector name="head" x="-75" y="-333"/><string name="_hash" value="2dc667ad1fd4663080b0a7b712776abac362a4352d22557f767bf73da41703bb"/><string name="_outlink" value="Mob/8880831.img/attack3/12"/></canvas><canvas name="13" width="1" height="1"><vector name="origin" x="370" y="749"/><int name="z" value="0"/><int name="delay" value="90"/><vector name="lt" x="-183" y="-408"/><vector name="rb" x="180" y="7"/><vector name="head" x="-75" y="-333"/><string name="_hash" value="b3f585f839905a49c86737d0fac11ed0ce3f4df2745f7f9eeb502360f25ca491"/><string name="_outlink" value="Mob/8880831.img/attack3/13"/></canvas><canvas name="14" width="1" height="1"><vector name="origin" x="368" y="720"/><int name="z" value="0"/><int name="delay" value="90"/><vector name="lt" x="-183" y="-408"/><vector name="rb" x="180" y="7"/><vector name="head" x="-75" y="-333"/><string name="_hash" value="b552a9246cdaddd2548b1a8941436a3f46c65d2cbb6b505da7796c972e0297d4"/><string name="_outlink" value="Mob/8880831.img/attack3/14"/></canvas><canvas name="15" width="1" height="1"><vector name="origin" x="357" y="667"/><int name="z" value="0"/><int name="delay" value="90"/><vector name="lt" x="-183" y="-408"/><vector name="rb" x="180" y="7"/><vector name="head" x="-75" y="-333"/><string name="_hash" value="b9f410d83149719a3df44b5b9214b998f9e4f3b971077526da3afe915f7dc2bb"/><string name="_outlink" value="Mob/8880831.img/attack3/15"/></canvas><canvas name="16" width="1" height="1"><vector name="origin" x="349" y="665"/><int name="z" value="0"/><int name="delay" value="90"/><vector name="lt" x="-183" y="-408"/><vector name="rb" x="180" y="7"/><vector name="head" x="-75" y="-333"/><string name="_hash" value="ab32ea7c1493f6837ab7c999d5ecb1f30113bedeb11a95aa9f3aaf270ab23e67"/><string name="_outlink" value="Mob/8880831.img/attack3/16"/></canvas><canvas name="17" width="1" height="1"><vector name="origin" x="347" y="584"/><int name="z" value="0"/><int name="delay" value="90"/><vector name="lt" x="-183" y="-408"/><vector name="rb" x="180" y="7"/><vector name="head" x="-75" y="-333"/><string name="_hash" value="bc29ca6352cbbd99f15529c73845c972a707a72dba58b16b2295dd917f064caf"/><string name="_outlink" value="Mob/8880831.img/attack3/17"/></canvas><canvas name="18" width="1" height="1"><vector name="origin" x="339" y="576"/><int name="z" value="0"/><int name="delay" value="90"/><vector name="lt" x="-183" y="-408"/><vector name="rb" x="180" y="7"/><vector name="head" x="-75" y="-333"/><string name="_hash" value="e50c1bd2fd3035bb0af551fd805d0eacb8ec36f566511393e72787b94bfb3dfb"/><string name="_outlink" value="Mob/8880831.img/attack3/18"/></canvas><canvas name="19" width="1" height="1"><vector name="origin" x="395" y="572"/><int name="z" value="0"/><int name="delay" value="90"/><vector name="lt" x="-183" y="-408"/><vector name="rb" x="180" y="7"/><vector name="head" x="-75" y="-333"/><string name="_hash" value="cf6b563778250905e1a8de57ec97bb6f84071102742b35d1ea1a188429ec0701"/><string name="_outlink" value="Mob/8880831.img/attack3/19"/></canvas></imgdir><imgdir name="attack4"><imgdir name="info"><imgdir name="range"><vector name="lt" x="-500" y="-284"/><vector name="rb" x="0" y="0"/></imgdir><imgdir name="hit"><canvas name="0" width="1" height="1"><vector name="origin" x="76" y="93"/><int name="z" value="0"/><int name="delay" value="90"/><string name="_hash" value="9795a2fb86bd47f62fd6b0b4c80e2d8bdfb27beff5784ac22c9933d2620b099f"/><string name="_outlink" value="Mob/8880831.img/attack4/info/hit/0"/></canvas><canvas name="1" width="1" height="1"><vector name="origin" x="102" y="89"/><int name="z" value="0"/><int name="delay" value="90"/><string name="_hash" value="c6565f4a3359766743b2aa5647a6882854649813e904eec1d103fa663550c7b6"/><string name="_outlink" value="Mob/8880831.img/attack4/info/hit/1"/></canvas><canvas name="2" width="1" height="1"><vector name="origin" x="141" y="85"/><int name="z" value="0"/><int name="delay" value="90"/><string name="_hash" value="50f0f0f4a6b344807a67b96647adfe53a4c8bd3cb9bcc496955f6fadad9e2954"/><string name="_outlink" value="Mob/8880831.img/attack4/info/hit/2"/></canvas><canvas name="3" width="1" height="1"><vector name="origin" x="143" y="87"/><int name="z" value="0"/><int name="delay" value="90"/><string name="_hash" value="0ab2aeb19c0c110930af5dbaf48473a02df34e3c73c2db61c9807863a185dd03"/><string name="_outlink" value="Mob/8880831.img/attack4/info/hit/3"/></canvas><canvas name="4" width="1" height="1"><vector name="origin" x="146" y="89"/><int name="z" value="0"/><int name="delay" value="90"/><string name="_hash" value="da41d6b02fb214c5db3d740566fb3a5c3bd44f459091bf338af369e27b57a760"/><string name="_outlink" value="Mob/8880831.img/attack4/info/hit/4"/></canvas><canvas name="5" width="1" height="1"><vector name="origin" x="147" y="90"/><int name="z" value="0"/><int name="delay" value="90"/><string name="_hash" value="d8f1b60cbc9b93b8f21daf1c18e787e7edc29f32a35beb2d480067630b74e626"/><string name="_outlink" value="Mob/8880831.img/attack4/info/hit/5"/></canvas><canvas name="6" width="1" height="1"><vector name="origin" x="147" y="90"/><int name="z" value="0"/><int name="delay" value="90"/><string name="_hash" value="07af7bd5f32f8d2521d05f2bae261482eaf4ebf29f1913e41e1510f4506a4b9e"/><string name="_outlink" value="Mob/8880831.img/attack4/info/hit/6"/></canvas><canvas name="7" width="1" height="1"><vector name="origin" x="94" y="90"/><int name="z" value="0"/><int name="delay" value="90"/><string name="_hash" value="3d3bd2086e977dce9cc63182c5d108a266c02080474367fe5bf4e57e618895eb"/><string name="_outlink" value="Mob/8880831.img/attack4/info/hit/7"/></canvas><canvas name="8" width="1" height="1"><vector name="origin" x="94" y="90"/><int name="z" value="0"/><int name="delay" value="90"/><string name="_hash" value="b116b3c060fe2fb12ae81664e6f6dd8c0b897809f4bf93abfa6c346138dd39b2"/><string name="_outlink" value="Mob/8880831.img/attack4/info/hit/8"/></canvas><int name="attach" value="1"/></imgdir><int name="attackAfter" value="1020"/></imgdir><canvas name="0" width="1" height="1"><vector name="origin" x="392" y="516"/><int name="z" value="0"/><int name="delay" value="90"/><vector name="lt" x="-183" y="-408"/><vector name="rb" x="180" y="7"/><vector name="head" x="-75" y="-333"/><string name="_hash" value="ae985c03ec237a8dda7df75d8eb85f60875072173531579df4b8c12d708f0e1e"/><string name="_outlink" value="Mob/8880831.img/attack4/0"/></canvas><canvas name="1" width="1" height="1"><vector name="origin" x="638" y="519"/><int name="z" value="0"/><int name="delay" value="90"/><vector name="lt" x="-183" y="-408"/><vector name="rb" x="180" y="7"/><vector name="head" x="-75" y="-333"/><string name="_hash" value="828cb15f64b684f56cdef520423be1e391e0a3cf39fbc2de129505f32c7c521d"/><string name="_outlink" value="Mob/8880831.img/attack4/1"/></canvas><canvas name="2" width="1" height="1"><vector name="origin" x="638" y="522"/><int name="z" value="0"/><int name="delay" value="90"/><vector name="lt" x="-183" y="-408"/><vector name="rb" x="180" y="7"/><vector name="head" x="-75" y="-333"/><string name="_hash" value="a204f28e82340f2b61407c878e76a4e5e457844911fd463aa9063f921a79ea62"/><string name="_outlink" value="Mob/8880831.img/attack4/2"/></canvas><canvas name="3" width="1" height="1"><vector name="origin" x="637" y="526"/><int name="z" value="0"/><int name="delay" value="90"/><vector name="lt" x="-183" y="-408"/><vector name="rb" x="180" y="7"/><vector name="head" x="-75" y="-333"/><string name="_hash" value="b85177e2b10684c5f310a944d9b59a939e5613507effe4420d5eb8fa01748459"/><string name="_outlink" value="Mob/8880831.img/attack4/3"/></canvas><canvas name="4" width="1" height="1"><vector name="origin" x="650" y="529"/><int name="z" value="0"/><int name="delay" value="90"/><vector name="lt" x="-183" y="-408"/><vector name="rb" x="180" y="7"/><vector name="head" x="-75" y="-333"/><string name="_hash" value="c6287ca8873caa8d479444f4ba36df57d3e1d290f7c68587d267972aaf48a65c"/><string name="_outlink" value="Mob/8880831.img/attack4/4"/></canvas><canvas name="5" width="1" height="1"><vector name="origin" x="841" y="532"/><int name="z" value="0"/><int name="delay" value="90"/><vector name="lt" x="-183" y="-408"/><vector name="rb" x="180" y="7"/><vector name="head" x="-75" y="-333"/><string name="_hash" value="4378b5389e2bd7b19e597ffb98f04b23a2a4e8882b16306e1203fa6631830d63"/><string name="_outlink" value="Mob/8880831.img/attack4/5"/></canvas><canvas name="6" width="1" height="1"><vector name="origin" x="975" y="535"/><int name="z" value="0"/><int name="delay" value="90"/><vector name="lt" x="-183" y="-408"/><vector name="rb" x="180" y="7"/><vector name="head" x="-75" y="-333"/><string name="_hash" value="0b0c3d0beda74d68482d2f9c25d608be67e4f9121594f6f33fbf18875762c368"/><string name="_outlink" value="Mob/8880831.img/attack4/6"/></canvas><canvas name="7" width="1" height="1"><vector name="origin" x="1052" y="538"/><int name="z" value="0"/><int name="delay" value="90"/><vector name="lt" x="-183" y="-408"/><vector name="rb" x="180" y="7"/><vector name="head" x="-75" y="-333"/><string name="_hash" value="44db7d4671f3e7ef939fc12da3712daf414a2d4b2a8d1a81023f4bbb784e0def"/><string name="_outlink" value="Mob/8880831.img/attack4/7"/></canvas><canvas name="8" width="1" height="1"><vector name="origin" x="1091" y="542"/><int name="z" value="0"/><int name="delay" value="90"/><vector name="lt" x="-183" y="-408"/><vector name="rb" x="180" y="7"/><vector name="head" x="-75" y="-333"/><string name="_hash" value="3ad6055bf65f8595e674ef97d5c034e1dcd3424c32460264e3bc4b7f8e22f2af"/><string name="_outlink" value="Mob/8880831.img/attack4/8"/></canvas><canvas name="9" width="1" height="1"><vector name="origin" x="1130" y="545"/><int name="z" value="0"/><int name="delay" value="90"/><vector name="lt" x="-183" y="-408"/><vector name="rb" x="180" y="7"/><vector name="head" x="-75" y="-333"/><string name="_hash" value="8fe4a032103b18917b443d07ad7fc064063459e843eda83c3d69da118db608dc"/><string name="_outlink" value="Mob/8880831.img/attack4/9"/></canvas><canvas name="10" width="1" height="1"><vector name="origin" x="1091" y="497"/><int name="z" value="0"/><int name="delay" value="90"/><vector name="lt" x="-183" y="-408"/><vector name="rb" x="180" y="7"/><vector name="head" x="-75" y="-333"/><string name="_hash" value="3c69af7644e9c83c04566d179997b24d01443cf319f3f8869ca2301ede60d3d5"/><string name="_outlink" value="Mob/8880831.img/attack4/10"/></canvas><canvas name="11" width="1" height="1"><vector name="origin" x="420" y="542"/><int name="z" value="0"/><int name="delay" value="90"/><vector name="lt" x="-183" y="-408"/><vector name="rb" x="180" y="7"/><vector name="head" x="-75" y="-333"/><string name="_hash" value="a284c5224529a9a9a5bd4f50bc1ef8dbea8bc54109bace78bab476afd2aaa398"/><string name="_outlink" value="Mob/8880831.img/attack4/11"/></canvas><canvas name="12" width="1" height="1"><vector name="origin" x="403" y="546"/><int name="z" value="0"/><int name="delay" value="90"/><vector name="lt" x="-183" y="-408"/><vector name="rb" x="180" y="7"/><vector name="head" x="-75" y="-333"/><string name="_hash" value="faf05362b4253147fb680702f399630950ab3d53deda2de2dcf015f8ba245c44"/><string name="_outlink" value="Mob/8880831.img/attack4/12"/></canvas><canvas name="13" width="1" height="1"><vector name="origin" x="419" y="549"/><int name="z" value="0"/><int name="delay" value="90"/><vector name="lt" x="-183" y="-408"/><vector name="rb" x="180" y="7"/><vector name="head" x="-75" y="-333"/><string name="_hash" value="87a12a5293a8b2069ff9baf6c112c0e014164dc950a8061c980425cdb4e6b2ec"/><string name="_outlink" value="Mob/8880831.img/attack4/13"/></canvas><canvas name="14" width="1" height="1"><vector name="origin" x="419" y="501"/><int name="z" value="0"/><int name="delay" value="90"/><vector name="lt" x="-183" y="-408"/><vector name="rb" x="180" y="7"/><vector name="head" x="-75" y="-333"/><string name="_hash" value="3125d1c015e665c895fbd92a614dccbbe0af47465f24fe65efdb3b2c36e7c4a8"/><string name="_outlink" value="Mob/8880831.img/attack4/14"/></canvas><canvas name="15" width="1" height="1"><vector name="origin" x="415" y="504"/><int name="z" value="0"/><int name="delay" value="90"/><vector name="lt" x="-183" y="-408"/><vector name="rb" x="180" y="7"/><vector name="head" x="-75" y="-333"/><string name="_hash" value="6c3b969f7ffae075d0d0f87dfe789013917acb9efce2dc3dc271dd2ac685188d"/><string name="_outlink" value="Mob/8880831.img/attack4/15"/></canvas><canvas name="16" width="1" height="1"><vector name="origin" x="421" y="508"/><int name="z" value="0"/><int name="delay" value="90"/><vector name="lt" x="-183" y="-408"/><vector name="rb" x="180" y="7"/><vector name="head" x="-75" y="-333"/><string name="_hash" value="f88550dcb2240575410d5be95fd6988a1e8b1bb3ba56a70ff5abcd826f7aa858"/><string name="_outlink" value="Mob/8880831.img/attack4/16"/></canvas><canvas name="17" width="1" height="1"><vector name="origin" x="428" y="511"/><int name="z" value="0"/><int name="delay" value="90"/><vector name="lt" x="-183" y="-408"/><vector name="rb" x="180" y="7"/><vector name="head" x="-75" y="-333"/><string name="_hash" value="ae68620b65a9b810692dd53784624b0f0dfdf84a367bdb0363013ec953ab9ffb"/><string name="_outlink" value="Mob/8880831.img/attack4/17"/></canvas><canvas name="18" width="1" height="1"><vector name="origin" x="402" y="514"/><int name="z" value="0"/><int name="delay" value="90"/><vector name="lt" x="-183" y="-408"/><vector name="rb" x="180" y="7"/><vector name="head" x="-75" y="-333"/><string name="_hash" value="50551277d2c53346798c7105dab2bbd298640da12bbfadad5ac5e5b328fe5a4f"/><string name="_outlink" value="Mob/8880831.img/attack4/18"/></canvas><canvas name="19" width="1" height="1"><vector name="origin" x="392" y="517"/><int name="z" value="0"/><int name="delay" value="90"/><vector name="lt" x="-183" y="-408"/><vector name="rb" x="180" y="7"/><vector name="head" x="-75" y="-333"/><string name="_hash" value="565ce2a32611adbbf478e67f27e2a8fd012e5b5cdc4e2e4d4171977fd57a274a"/><string name="_outlink" value="Mob/8880831.img/attack4/19"/></canvas></imgdir></imgdir>