<?xml version="1.0" encoding="UTF-8" standalone="yes"?><imgdir name="9834252.img"><imgdir name="info"><int name="level" value="200"/><int name="bodyAttack" value="1"/><int name="firstAttack" value="1"/><int name="maxHP" value="930000"/><int name="maxMP" value="30000"/><int name="speed" value="0"/><int name="PADamage" value="10260"/><int name="MADamage" value="10170"/><int name="pushed" value="11000"/><int name="acc" value="723"/><int name="eva" value="205"/><int name="exp" value="12694"/><int name="PDRate" value="10"/><int name="MDRate" value="10"/><int name="fs" value="10"/><int name="summonType" value="1"/><int name="category" value="1"/><string name="mobType" value="1N"/><int name="changeableMob" value="1"/><string name="changeableMob_Type" value="StrawberryFarm2"/><int name="minimap" value="1"/></imgdir><imgdir name="regen"><canvas name="0" width="359" height="291"><vector name="origin" x="194" y="217"/><int name="z" value="0"/><int name="delay" value="90"/><string name="_hash" value="1097f7edd31bcccbfa8d45e789f639f9b86fe656c44f1225905b6d34e31d1af0"/></canvas><canvas name="1" width="385" height="371"><vector name="origin" x="193" y="301"/><int name="z" value="0"/><int name="delay" value="90"/><string name="_hash" value="789fda404959c0f7dc302268374af9b8cc1f1b2f714c722a251c6e0748963735"/></canvas><canvas name="2" width="428" height="388"><vector name="origin" x="208" y="324"/><int name="z" value="0"/><int name="delay" value="90"/><string name="_hash" value="24268671ba8cb7f737018a9b763a3a23b8d0e2fb4b3f11b35ac332dcbe5d3b6c"/></canvas><canvas name="3" width="449" height="398"><vector name="origin" x="217" y="339"/><int name="z" value="0"/><int name="delay" value="90"/><string name="_hash" value="1e3f33a3edc44e67f6793394a7c155e11741c971a02ef5f9bd799e3f653fb6ae"/></canvas><canvas name="4" width="455" height="402"><vector name="origin" x="219" y="346"/><int name="z" value="0"/><int name="delay" value="90"/><string name="_hash" value="0460d71d8bd4e8d56de68faacc01b7b683837e3a6e5be23082feff208ec954f0"/></canvas><canvas name="5" width="457" height="396"><vector name="origin" x="217" y="342"/><int name="z" value="0"/><int name="delay" value="90"/><string name="_hash" value="a2f0568b8647e10dbd4eed34754311293ee739aacdb301f6672c3f681795c981"/></canvas><canvas name="6" width="469" height="392"><vector name="origin" x="225" y="344"/><int name="z" value="0"/><int name="delay" value="90"/><string name="_hash" value="47e7ea924e85590765048905524f65bd47380ec6d2bece7d47f1c0a2c217ac3a"/></canvas><canvas name="7" width="475" height="384"><vector name="origin" x="226" y="344"/><int name="z" value="0"/><int name="delay" value="90"/><string name="_hash" value="eda9fde17af90c6aa33225812ab76e51a09211363e366a70924ed9b9b45192f9"/></canvas><canvas name="8" width="458" height="374"><vector name="origin" x="216" y="347"/><int name="z" value="0"/><int name="delay" value="120"/><vector name="head" x="-11" y="-397"/><string name="_hash" value="58cf398089f58b5b2fd71007903f49993db56950a8a320581aa37b34c0a499dd"/></canvas><canvas name="9" width="406" height="380"><vector name="origin" x="195" y="364"/><int name="z" value="0"/><int name="delay" value="120"/><vector name="head" x="-11" y="-397"/><string name="_hash" value="15f4fee3416b7bf02023e0894908e723fd8a207f63068287b44fee13b3327164"/></canvas><canvas name="10" width="394" height="389"><vector name="origin" x="192" y="373"/><int name="z" value="0"/><int name="delay" value="120"/><vector name="head" x="-11" y="-397"/><string name="_hash" value="5256be06ea63025c20daeee2e36fe447837cf7383e583456d2fef5f81e2b1953"/></canvas><canvas name="11" width="380" height="400"><vector name="origin" x="189" y="384"/><int name="z" value="0"/><int name="delay" value="120"/><vector name="head" x="-11" y="-397"/><string name="_hash" value="6d8e70cdee9e8877a8e94098a56eb1e3dfe085fbd3dd070334c9e3ee4b9ba2b0"/></canvas><canvas name="12" width="369" height="402"><vector name="origin" x="184" y="386"/><int name="z" value="0"/><int name="delay" value="120"/><vector name="head" x="-11" y="-397"/><string name="_hash" value="afd843bad7074163e42ecc9599012e090df2705fc2d315a702e35d4fa957b921"/></canvas><canvas name="13" width="347" height="395"><vector name="origin" x="171" y="379"/><int name="z" value="0"/><int name="delay" value="120"/><vector name="head" x="-11" y="-397"/><string name="_hash" value="c62dd0c35f79c0b129d9924e75839804dac384101dfb7c541323c98026872934"/></canvas></imgdir><imgdir name="stand"><canvas name="0" width="282" height="284"><vector name="origin" x="145" y="268"/><int name="z" value="0"/><int name="delay" value="120"/><vector name="lt" x="-139" y="-253"/><vector name="rb" x="130" y="5"/><vector name="head" x="-22" y="-178"/><string name="_hash" value="fbe78e4a72a5f8c9145a80d4644dbc65efb691293aecb101bb67ba03094e3bda"/></canvas><canvas name="1" width="284" height="286"><vector name="origin" x="146" y="270"/><int name="z" value="0"/><int name="delay" value="120"/><vector name="lt" x="-139" y="-253"/><vector name="rb" x="130" y="5"/><vector name="head" x="-22" y="-178"/><string name="_hash" value="58c3bf6d6847fa4e45e7dc635624ab8c43662597844b92f0ae8b71f90519110c"/></canvas><canvas name="2" width="286" height="289"><vector name="origin" x="148" y="273"/><int name="z" value="0"/><int name="delay" value="120"/><vector name="lt" x="-139" y="-253"/><vector name="rb" x="130" y="5"/><vector name="head" x="-22" y="-178"/><string name="_hash" value="6d2a52d43bc94dfbee588c6490e4485da3c2cd140c0907f50372cdef227e74d0"/></canvas><canvas name="3" width="287" height="291"><vector name="origin" x="148" y="275"/><int name="z" value="0"/><int name="delay" value="120"/><vector name="lt" x="-139" y="-253"/><vector name="rb" x="130" y="5"/><vector name="head" x="-22" y="-178"/><string name="_hash" value="9f8b257df6243cba747dba974dac44229a468c8649fb9532835d529fddccba47"/></canvas><canvas name="4" width="289" height="292"><vector name="origin" x="149" y="276"/><int name="z" value="0"/><int name="delay" value="120"/><vector name="lt" x="-139" y="-253"/><vector name="rb" x="130" y="5"/><vector name="head" x="-22" y="-178"/><string name="_hash" value="c6fdd53ddd094b7ef9a8866305f0bd7e7a869226f55dfb5d6c7cbe70ef7d77a5"/></canvas><canvas name="5" width="291" height="293"><vector name="origin" x="150" y="277"/><int name="z" value="0"/><int name="delay" value="120"/><vector name="lt" x="-139" y="-253"/><vector name="rb" x="130" y="5"/><vector name="head" x="-22" y="-178"/><string name="_hash" value="1a356d9a5fb15685964c277b482ff7db09ea7866095dc3ade5b821fcf85a2a6a"/></canvas><canvas name="6" width="293" height="293"><vector name="origin" x="151" y="277"/><int name="z" value="0"/><int name="delay" value="120"/><vector name="lt" x="-139" y="-253"/><vector name="rb" x="130" y="5"/><vector name="head" x="-22" y="-178"/><string name="_hash" value="9b3326b744710050f1a97a2600cd8ca08dcd5f52dd1e3eff0922d094b2903092"/></canvas><canvas name="7" width="296" height="288"><vector name="origin" x="152" y="272"/><int name="z" value="0"/><int name="delay" value="120"/><vector name="lt" x="-139" y="-253"/><vector name="rb" x="130" y="5"/><vector name="head" x="-22" y="-178"/><string name="_hash" value="c3179bd4b2a99065ffcca3ab86f683e6ead6e1892f0ee1b5e070b53bc48481c0"/></canvas><canvas name="8" width="297" height="290"><vector name="origin" x="153" y="274"/><int name="z" value="0"/><int name="delay" value="120"/><vector name="lt" x="-139" y="-253"/><vector name="rb" x="130" y="5"/><vector name="head" x="-22" y="-178"/><string name="_hash" value="565f8630d2c711b3af0e88f124dfe952472a8cab7cdc38b64df3c13f4d354d66"/></canvas><canvas name="9" width="295" height="289"><vector name="origin" x="152" y="273"/><int name="z" value="0"/><int name="delay" value="120"/><vector name="lt" x="-139" y="-253"/><vector name="rb" x="130" y="5"/><vector name="head" x="-22" y="-178"/><string name="_hash" value="7656bb2b77be6eac1219b2c3a7183229f5bc83f006e6fad003c666c0e827e114"/></canvas><canvas name="10" width="293" height="285"><vector name="origin" x="151" y="269"/><int name="z" value="0"/><int name="delay" value="120"/><vector name="lt" x="-139" y="-253"/><vector name="rb" x="130" y="5"/><vector name="head" x="-22" y="-178"/><string name="_hash" value="ba4f0ebcd9701e5504ba8adce1e01b5bb6d5abdc4d914cef47804e929f6e1cd8"/></canvas><canvas name="11" width="291" height="283"><vector name="origin" x="150" y="267"/><int name="z" value="0"/><int name="delay" value="120"/><vector name="lt" x="-139" y="-253"/><vector name="rb" x="130" y="5"/><vector name="head" x="-22" y="-178"/><string name="_hash" value="8e6527429a9f9a2d10ad0afdb02be705630d2d45e18de4d78b48c6c28e1edd4f"/></canvas><canvas name="12" width="289" height="286"><vector name="origin" x="149" y="270"/><int name="z" value="0"/><int name="delay" value="120"/><vector name="lt" x="-139" y="-253"/><vector name="rb" x="130" y="5"/><vector name="head" x="-22" y="-178"/><string name="_hash" value="9302ed10b3d634d7d3dd41bd39c7aa86755a426c7e5be72caefa73022d549bb7"/></canvas><canvas name="13" width="287" height="286"><vector name="origin" x="148" y="270"/><int name="z" value="0"/><int name="delay" value="120"/><vector name="lt" x="-139" y="-253"/><vector name="rb" x="130" y="5"/><vector name="head" x="-22" y="-178"/><string name="_hash" value="10f50deaefe310e750bcaf98907b0a7c419b71f0453d12251e78b8048066ebf3"/></canvas><canvas name="14" width="285" height="285"><vector name="origin" x="147" y="269"/><int name="z" value="0"/><int name="delay" value="120"/><vector name="lt" x="-139" y="-253"/><vector name="rb" x="130" y="5"/><vector name="head" x="-22" y="-178"/><string name="_hash" value="00734be2f8bceb00d160f0dcf7aa8e9fda51cf8424ab06869bf0a93aa4fc05de"/></canvas><canvas name="15" width="283" height="285"><vector name="origin" x="146" y="269"/><int name="z" value="0"/><int name="delay" value="120"/><vector name="lt" x="-139" y="-253"/><vector name="rb" x="130" y="5"/><vector name="head" x="-22" y="-178"/><string name="_hash" value="cf930d7dd29dc06d79919a12831a4c7a98c674ff696f3e0fab16d6cc23a1246e"/></canvas></imgdir><imgdir name="move"><canvas name="0" width="286" height="284"><vector name="origin" x="155" y="268"/><int name="z" value="0"/><int name="delay" value="120"/><vector name="lt" x="-139" y="-253"/><vector name="rb" x="130" y="5"/><vector name="head" x="-22" y="-178"/><string name="_hash" value="2a716916e7c81909686838f2c18516f447a0e272fc526f0ff9fd13a9f7ed5db6"/></canvas><canvas name="1" width="288" height="286"><vector name="origin" x="155" y="270"/><int name="z" value="0"/><int name="delay" value="120"/><vector name="lt" x="-139" y="-253"/><vector name="rb" x="130" y="5"/><vector name="head" x="-22" y="-178"/><string name="_hash" value="1469e859139617e0cbbf80990d6dfda8d39dcaa68ee0abb1f6b0a80621a96d92"/></canvas><canvas name="2" width="290" height="289"><vector name="origin" x="156" y="273"/><int name="z" value="0"/><int name="delay" value="120"/><vector name="lt" x="-139" y="-253"/><vector name="rb" x="130" y="5"/><vector name="head" x="-22" y="-178"/><string name="_hash" value="27d4c0c583f0f52f83a2572d37c0f02c8aaa0c24ec8bde2e5af490e74406e102"/></canvas><canvas name="3" width="290" height="291"><vector name="origin" x="155" y="275"/><int name="z" value="0"/><int name="delay" value="120"/><vector name="lt" x="-139" y="-253"/><vector name="rb" x="130" y="5"/><vector name="head" x="-22" y="-178"/><string name="_hash" value="ab737fa79afd5f808c5daa17f1cf0836bbf38cbd6426c0670c13f9236b7fa3e5"/></canvas><canvas name="4" width="290" height="292"><vector name="origin" x="155" y="276"/><int name="z" value="0"/><int name="delay" value="120"/><vector name="lt" x="-139" y="-253"/><vector name="rb" x="130" y="5"/><vector name="head" x="-22" y="-178"/><string name="_hash" value="82105d16ce2bd97e1ca2afc7ae1d0711ac4c8c2e5600cc0fb5bec9898647fc02"/></canvas><canvas name="5" width="291" height="291"><vector name="origin" x="155" y="275"/><int name="z" value="0"/><int name="delay" value="120"/><vector name="lt" x="-139" y="-253"/><vector name="rb" x="130" y="5"/><vector name="head" x="-22" y="-178"/><string name="_hash" value="c9afaa1596f23e59ea7d8cb3bf38ef9659fed963c4c1d6ed82c75b6d3a6a2aba"/></canvas><canvas name="6" width="291" height="289"><vector name="origin" x="155" y="273"/><int name="z" value="0"/><int name="delay" value="120"/><vector name="lt" x="-139" y="-253"/><vector name="rb" x="130" y="5"/><vector name="head" x="-22" y="-178"/><string name="_hash" value="1f42dc25b399d35b8e090b84e6bef38ef19e119948aff3a884e22c3808b40873"/></canvas><canvas name="7" width="291" height="282"><vector name="origin" x="155" y="266"/><int name="z" value="0"/><int name="delay" value="120"/><vector name="lt" x="-139" y="-253"/><vector name="rb" x="130" y="5"/><vector name="head" x="-22" y="-178"/><string name="_hash" value="599bec0c56af60db21e1af6216308e9c8bb0a69a6d96d2034f1d7d70c9e166f2"/></canvas><canvas name="8" width="289" height="282"><vector name="origin" x="155" y="266"/><int name="z" value="0"/><int name="delay" value="120"/><vector name="lt" x="-139" y="-253"/><vector name="rb" x="130" y="5"/><vector name="head" x="-22" y="-178"/><string name="_hash" value="5d045c23eb340c21f72988aa2a13d8b1254fdbeaa64c75d230c81869ed7596e6"/></canvas><canvas name="9" width="289" height="283"><vector name="origin" x="155" y="267"/><int name="z" value="0"/><int name="delay" value="120"/><vector name="lt" x="-139" y="-253"/><vector name="rb" x="130" y="5"/><vector name="head" x="-22" y="-178"/><string name="_hash" value="fbe189a88c41a8e0a70ccb889bfcb04aa3f6bef77fcf43ba4f5610bab7ec849e"/></canvas><canvas name="10" width="287" height="281"><vector name="origin" x="155" y="265"/><int name="z" value="0"/><int name="delay" value="120"/><vector name="lt" x="-139" y="-253"/><vector name="rb" x="130" y="5"/><vector name="head" x="-22" y="-178"/><string name="_hash" value="e6d988f25273d3e140747411e05f2ea1691f5228d59982a7c437393e8f67798e"/></canvas><canvas name="11" width="287" height="281"><vector name="origin" x="155" y="265"/><int name="z" value="0"/><int name="delay" value="120"/><vector name="lt" x="-139" y="-253"/><vector name="rb" x="130" y="5"/><vector name="head" x="-22" y="-178"/><string name="_hash" value="30b9ad7f737fa53f6b3bbc54b3eb9d78da8d4447bd7645e5e01c68d941fd4576"/></canvas><canvas name="12" width="286" height="286"><vector name="origin" x="155" y="270"/><int name="z" value="0"/><int name="delay" value="120"/><vector name="lt" x="-139" y="-253"/><vector name="rb" x="130" y="5"/><vector name="head" x="-22" y="-178"/><string name="_hash" value="89c4fc61117ed40e5a763894d26ee9aab6b1ea1f575e4be054ab201f1eb9289d"/></canvas><canvas name="13" width="285" height="286"><vector name="origin" x="155" y="270"/><int name="z" value="0"/><int name="delay" value="120"/><vector name="lt" x="-139" y="-253"/><vector name="rb" x="130" y="5"/><vector name="head" x="-22" y="-178"/><string name="_hash" value="f52f57098373d77230b6742367711d9b0bd8f157548f59378db138416930c001"/></canvas><canvas name="14" width="286" height="285"><vector name="origin" x="155" y="269"/><int name="z" value="0"/><int name="delay" value="120"/><vector name="lt" x="-139" y="-253"/><vector name="rb" x="130" y="5"/><vector name="head" x="-22" y="-178"/><string name="_hash" value="1a8baa47c4649724849148508e2bd0815d94f4b659f0d7692e139193a9361712"/></canvas><canvas name="15" width="285" height="285"><vector name="origin" x="155" y="269"/><int name="z" value="0"/><int name="delay" value="120"/><vector name="lt" x="-139" y="-253"/><vector name="rb" x="130" y="5"/><vector name="head" x="-22" y="-178"/><string name="_hash" value="550c6edebd2aa6c0381ad936c133306e02b8e258f218f282f0a0f7983aa8d095"/></canvas></imgdir><imgdir name="hit1"><canvas name="0" width="323" height="287"><vector name="origin" x="127" y="271"/><int name="z" value="0"/><int name="delay" value="120"/><vector name="lt" x="-139" y="-253"/><vector name="rb" x="130" y="5"/><vector name="head" x="-22" y="-178"/><string name="_hash" value="558ccbc81a2bc59fa7def83515bdacc9aff1e7256b41fadc1518970bf2f721b9"/></canvas></imgdir><imgdir name="die1"><canvas name="0" width="595" height="392"><vector name="origin" x="366" y="268"/><int name="z" value="0"/><int name="delay" value="60"/><vector name="head" x="21" y="-364"/><string name="_hash" value="16b5b4a7eed19428f5918dc9fd538ae7db6b01fb795cd98a7c6dbf3bc94a4c1b"/></canvas><canvas name="1" width="323" height="287"><vector name="origin" x="127" y="271"/><int name="z" value="0"/><int name="delay" value="60"/><vector name="head" x="21" y="-364"/><string name="_hash" value="b4aea4ddeb876010d67139555e38244ff823c45eba30d0928521d949c4efdeb2"/></canvas><canvas name="2" width="304" height="282"><vector name="origin" x="123" y="266"/><int name="z" value="0"/><int name="delay" value="60"/><vector name="head" x="21" y="-364"/><string name="_hash" value="af94ae989144fdcd89a7a8b7c82f080e0792da16fe310fa541d15a79f4252727"/></canvas><canvas name="3" width="295" height="279"><vector name="origin" x="119" y="263"/><int name="z" value="0"/><int name="delay" value="60"/><vector name="head" x="21" y="-364"/><string name="_hash" value="1626dbf9988db80917a57a9e0a912f9d633893bbe4577674713e6760596c8422"/></canvas><canvas name="4" width="284" height="278"><vector name="origin" x="117" y="262"/><int name="z" value="0"/><int name="delay" value="60"/><vector name="head" x="21" y="-364"/><string name="_hash" value="604b666719161880a18be0797c98f6d50861f31c9531054d11c0de5073c35df8"/></canvas><canvas name="5" width="284" height="282"><vector name="origin" x="116" y="266"/><int name="z" value="0"/><int name="delay" value="60"/><vector name="head" x="21" y="-364"/><string name="_hash" value="7c3b9db026dc1effe7b1a1a0f03a5e6dc76588fcd73b075c25a22b38f7ffdc66"/></canvas><canvas name="6" width="283" height="283"><vector name="origin" x="114" y="267"/><int name="z" value="0"/><int name="delay" value="60"/><vector name="head" x="21" y="-364"/><string name="_hash" value="2d0981e3721f431b3d15e5e9a0f74585485c47fe0b4a8f1e412e42559ede446d"/></canvas><canvas name="7" width="281" height="281"><vector name="origin" x="112" y="266"/><int name="z" value="0"/><int name="delay" value="60"/><vector name="head" x="21" y="-364"/><string name="_hash" value="f73d71bbe5ccf418a17bce5103277d28b0852842561f0186ebb835e4c37af875"/></canvas><canvas name="8" width="279" height="281"><vector name="origin" x="110" y="266"/><int name="z" value="0"/><int name="delay" value="60"/><vector name="head" x="21" y="-364"/><string name="_hash" value="1b89a1324ecfad66ccc2f2be8aeb25bd25dc516d870d0899b71c25b332c90cf5"/></canvas><canvas name="9" width="277" height="184"><vector name="origin" x="109" y="199"/><int name="z" value="0"/><int name="delay" value="60"/><vector name="head" x="21" y="-364"/><string name="_hash" value="4f9e570b1097a6d07275316868f5dcb1684d9d6fcca7475aaa0300b80b8311bc"/></canvas><canvas name="10" width="283" height="183"><vector name="origin" x="121" y="205"/><int name="z" value="0"/><int name="delay" value="60"/><vector name="head" x="21" y="-364"/><string name="_hash" value="698f647d017785b623fa48314abfd0b01a988a81716a7929e60a5dcec835e8ce"/></canvas><canvas name="11" width="291" height="245"><vector name="origin" x="129" y="209"/><int name="z" value="0"/><int name="delay" value="60"/><vector name="head" x="21" y="-364"/><string name="_hash" value="5d72bb52d118b9bbf9677a93a1911208021b17b4630d571da46da09b3add5006"/></canvas><canvas name="12" width="300" height="251"><vector name="origin" x="138" y="212"/><int name="z" value="0"/><int name="delay" value="60"/><vector name="head" x="21" y="-364"/><string name="_hash" value="40530428abf01ad9fd90b5adf1520b9695e48d4ff59c9f707296603cff2e3ec4"/></canvas><canvas name="13" width="311" height="287"><vector name="origin" x="149" y="213"/><int name="z" value="0"/><int name="delay" value="60"/><vector name="head" x="21" y="-364"/><string name="_hash" value="673a71fb529e2871e62700ca79c91a55f35716b425128021d02242950951c020"/></canvas><canvas name="14" width="327" height="301"><vector name="origin" x="154" y="212"/><int name="z" value="0"/><int name="delay" value="60"/><vector name="head" x="-11" y="-397"/><string name="_hash" value="2697f477a36075d15a998b248ce1533badae06edef18c5286e95c192f32cdf27"/></canvas><canvas name="15" width="366" height="348"><vector name="origin" x="163" y="249"/><int name="z" value="0"/><int name="delay" value="60"/><vector name="head" x="-11" y="-397"/><string name="_hash" value="2a0473e9bb185a724b848c006a959b262f345dcc41989865d88a8996dc52c42b"/></canvas><canvas name="16" width="401" height="363"><vector name="origin" x="187" y="259"/><int name="z" value="0"/><int name="delay" value="60"/><vector name="head" x="-11" y="-397"/><string name="_hash" value="cf7062130e516427aa8546d9540476d67cd145b76afaf22bc798e8c056ae19c4"/></canvas><canvas name="17" width="467" height="376"><vector name="origin" x="231" y="254"/><int name="z" value="0"/><int name="delay" value="60"/><vector name="head" x="-11" y="-397"/><string name="_hash" value="88dc886ddda592363b2786b1c058d1c4e6b07b98c3d3eefc3f99877e9c918f93"/></canvas><canvas name="18" width="463" height="409"><vector name="origin" x="229" y="287"/><int name="z" value="0"/><int name="delay" value="60"/><vector name="head" x="-11" y="-397"/><string name="_hash" value="edba536c2f9f9f58b0199fb0655fc972231e0c8798b79f9fb1bf1ac27777211b"/></canvas><canvas name="19" width="456" height="410"><vector name="origin" x="225" y="288"/><int name="z" value="0"/><int name="delay" value="60"/><vector name="head" x="-11" y="-397"/><string name="_hash" value="280dbb591a5c4c36bf0842f265dfc89b8541b03f811208fd77f418bec05c0024"/></canvas><canvas name="20" width="447" height="407"><vector name="origin" x="217" y="285"/><int name="z" value="0"/><int name="delay" value="60"/><vector name="head" x="-11" y="-397"/><string name="_hash" value="ee64b94a5d754b55f3222603b3f83bc08d3cb3ec18e859c24899efd443254936"/></canvas><canvas name="21" width="445" height="406"><vector name="origin" x="214" y="284"/><int name="z" value="0"/><int name="delay" value="60"/><vector name="head" x="-11" y="-397"/><string name="_hash" value="10fa46ed2e2ce93e9b68c486ea7c04c886eb874b94214bea9f1d46e2cd3776e4"/></canvas><canvas name="22" width="444" height="401"><vector name="origin" x="210" y="279"/><int name="z" value="0"/><int name="delay" value="60"/><vector name="head" x="-11" y="-397"/><string name="_hash" value="361dcf1736a40f0fea8670a7241aafe723c3da634d2cccdfa8a2976b158c9225"/></canvas><canvas name="23" width="441" height="399"><vector name="origin" x="210" y="277"/><int name="z" value="0"/><int name="delay" value="60"/><vector name="head" x="-11" y="-397"/><string name="_hash" value="6b861e7cb09069a23a87d1277054b1938054c55197caf2bec451263159dcfdf3"/></canvas><canvas name="24" width="438" height="398"><vector name="origin" x="207" y="276"/><int name="z" value="0"/><int name="delay" value="60"/><vector name="head" x="-11" y="-397"/><string name="_hash" value="4ecbb3078c5fc3ecdbe85faffd4be4fd904a9b68e9bdaf7c1eeaef1a1c74b060"/></canvas><canvas name="25" width="444" height="398"><vector name="origin" x="209" y="276"/><int name="z" value="0"/><int name="delay" value="60"/><vector name="head" x="-11" y="-397"/><string name="_hash" value="46f2a3023fb5906ac2cbdee7891487b15203ae9818f53b656e0bacba120f94d7"/></canvas><canvas name="26" width="450" height="396"><vector name="origin" x="211" y="274"/><int name="z" value="0"/><int name="delay" value="60"/><vector name="head" x="-11" y="-397"/><string name="_hash" value="18af180aa568e7dd9919a69282e2bf9024cd2c191f1ec6933d13b3391e7172e5"/></canvas><canvas name="27" width="455" height="393"><vector name="origin" x="213" y="271"/><int name="z" value="0"/><int name="delay" value="60"/><vector name="head" x="-11" y="-397"/><string name="_hash" value="a0bb909fdce49a46797e89178602d922acd5a71c7c16d03c3e16b035d72f94be"/></canvas><canvas name="28" width="450" height="388"><vector name="origin" x="212" y="266"/><int name="z" value="0"/><int name="delay" value="60"/><vector name="head" x="-11" y="-397"/><string name="_hash" value="ca1a45027b6a90648cc73f7a5f2430b88e733d9dc9b2e05bfb3329c3a4aa4ef2"/></canvas><canvas name="29" width="455" height="384"><vector name="origin" x="213" y="262"/><int name="z" value="0"/><int name="delay" value="60"/><vector name="head" x="21" y="-364"/><string name="_hash" value="5d4e51908c98bc878eee7c78e4e79d1b3612d4a6922afac3a1a0dac9545fa23c"/></canvas></imgdir></imgdir>